Workbook

Sheet SUNPHARMA Beta Calc
C2: SUNPHARMA.NS
A3: Price | B3: Close | C3: Close | D3: Return | E3: Return | H3: Covariance(Market/company) | I3: Variance (Market)
A4: Ticker | B4: ^CNXPHARMA | C4: SUNPHARMA.NS | D4: Nifty | E4: Company | H4: =_xlfn.COVARIANCE.S(D7:D252,E7:E252) -> 9.884811e-05 | I4: =_xlfn.VAR.S(D7:D252) -> 0.00010123143
A5: Date
A6: 45383 | B6: 19207.9 | C6: 1598.6888 | H6: Beta
A7: 45384 | B7: 19185.15 | C7: 1591.8202 | D7: =(B7-B6)/B6 -> -0.0011844085 | E7: =(C7-C6)/C6 -> -0.0042964285 | H7: =H4/I4 -> 0.97645672
A8: 45385 | B8: 19153.051 | C8: 1589.4652 | D8: =(B8-B7)/B7 -> -0.0016731487 | E8: =(C8-C7)/C7 -> -0.0014794262
A9: 45386 | B9: 19125.199 | C9: 1588.9746 | D9: =(B9-B8)/B8 -> -0.001454158 | E9: =(C9-C8)/C8 -> -0.00030865764 | H9: Market Return
A10: 45387 | B10: 19160.75 | C10: 1578.8187 | D10: =(B10-B9)/B9 -> 0.001858845 | E10: =(C10-C9)/C9 -> -0.0063914702 | H10: =AVERAGE(D7:D252) -> 0.00043962859
A11: 45390 | B11: 19218.85 | C11: 1569.6931 | D11: =(B11-B10)/B10 -> 0.00303222 | E11: =(C11-C10)/C10 -> -0.0057800241
A12: 45391 | B12: 19182.301 | C12: 1572.4899 | D12: =(B12-B11)/B11 -> -0.0019017178 | E12: =(C12-C11)/C11 -> 0.0017817196
A13: 45392 | B13: 19117 | C13: 1573.9617 | D13: =(B13-B12)/B12 -> -0.0034042205 | E13: =(C13-C12)/C12 -> 0.00093596899
A14: 45394 | B14: 18788.65 | C14: 1511.113 | D14: =(B14-B13)/B13 -> -0.017175792 | E14: =(C14-C13)/C13 -> -0.039930218
A15: 45397 | B15: 18617.65 | C15: 1511.1622 | D15: =(B15-B14)/B14 -> -0.0091012391 | E15: =(C15-C14)/C14 -> 3.2555034e-05
A16: 45398 | B16: 18695.6 | C16: 1508.7091 | D16: =(B16-B15)/B15 -> 0.0041868451 | E16: =(C16-C15)/C15 -> -0.0016233366
A17: 45400 | B17: 18525.75 | C17: 1487.9557 | D17: =(B17-B16)/B16 -> -0.0090850046 | E17: =(C17-C16)/C16 -> -0.013755745
A18: 45401 | B18: 18404.6 | C18: 1494.2357 | D18: =(B18-B17)/B17 -> -0.0065395674 | E18: =(C18-C17)/C17 -> 0.0042205755
A19: 45404 | B19: 18643 | C19: 1511.2112 | D19: =(B19-B18)/B18 -> 0.012953305 | E19: =(C19-C18)/C18 -> 0.011360633
A20: 45405 | B20: 18463.75 | C20: 1456.8013 | D20: =(B20-B19)/B19 -> -0.0096148689 | E20: =(C20-C19)/C19 -> -0.036004175
A21: 45406 | B21: 18586.199 | C21: 1457.8806 | D21: =(B21-B20)/B20 -> 0.0066318716 | E21: =(C21-C20)/C20 -> 0.00074090113
A22: 45407 | B22: 18878.15 | C22: 1491.6354 | D22: =(B22-B21)/B21 -> 0.015707955 | E22: =(C22-C21)/C21 -> 0.023153309
... A252: 45744 | B252: 21137.449 | C252: 1717.8495 | D252: =(B252-B251)/B251 -> -0.0064723948 | E252: =(C252-C251)/C251 -> 0.0018770124

Sheet Sun Pharmaceutical Industries
C2: Sun Pharmaceutical Industries | P2: SUNPHARMA.NS
P3: Price | Q3: Close | R3: Close | S3: Return | T3: Return | W3: Covariance(Market/company) | X3: Variance (Market)
B4: Balance Sheet of Sun Pharmaceutical Industries (in Rs. Cr.) | C4: 46105 | F4: Profit & Loss account of Sun Pharmaceutical Industries (in Rs. Cr.) | G4: 46105 | P4: Ticker | Q4: ^CNXPHARMA | R4: SUNPHARMA.NS | S4: Nifty | T4: Company | W4: =_xlfn.COVARIANCE.S(S7:S252,T7:T252) -> 9.884811e-05 | X4: =_xlfn.VAR.S(S7:S252) -> 0.00010123143
C5: 12 mths | G5: 12 mths | P5: Date
B6: EQUITIES AND LIABILITIES | F6: INCOME | P6: 45383 | Q6: 19207.9 | R6: 1598.6888 | W6: Beta
B7: SHAREHOLDER'S FUNDS | F7: Revenue From Operations [Gross] | G7: 47758.45 | P7: 45384 | Q7: 19185.15 | R7: 1591.8202 | S7: =(Q7-Q6)/Q6 -> -0.0011844085 | T7: =(R7-R6)/R6 -> -0.0042964285 | W7: =W4/X4 -> 0.97645672
B8: Equity Share Capital | C8: 239.93 | F8: Less: Excise/Sevice Tax/Other Levies | G8: 0 | P8: 45385 | Q8: 19153.051 | R8: 1589.4652 | S8: =(Q8-Q7)/Q7 -> -0.0016731487 | T8: =(R8-R7)/R7 -> -0.0014794262
B9: Total Share Capital | C9: 239.93 | F9: Revenue From Operations [Net] | G9: 47758.45 | P9: 45386 | Q9: 19125.199 | R9: 1588.9746 | S9: =(Q9-Q8)/Q8 -> -0.001454158 | T9: =(R9-R8)/R8 -> -0.00030865764 | W9: Market Return
B10: Reserves and Surplus | C10: 63426.82 | F10: Total Operating Revenues | G10: 48496.85 | P10: 45387 | Q10: 19160.75 | R10: 1578.8187 | S10: =(Q10-Q9)/Q9 -> 0.001858845 | T10: =(R10-R9)/R9 -> -0.0063914702 | W10: =AVERAGE(S7:S252) -> 0.00043962859
B11: Total Reserves and Surplus | C11: 63426.82 | F11: Other Income | G11: 1354.19 | P11: 45390 | Q11: 19218.85 | R11: 1569.6931 | S11: =(Q11-Q10)/Q10 -> 0.00303222 | T11: =(R11-R10)/R10 -> -0.0057800241
B12: Total Shareholders Funds | C12: 63666.75 | F12: Total Revenue | G12: 49851.04 | P12: 45391 | Q12: 19182.301 | R12: 1572.4899 | S12: =(Q12-Q11)/Q11 -> -0.0019017178 | T12: =(R12-R11)/R11 -> 0.0017817196
B13: Minority Interest | C13: 3439.22 | F13: EXPENSES | J13: Total Debt | K13: =C15 + C21 -> 2845.69 | L13: =_xlfn.FORMULATEXT(K13) -> =C15 + C21 | M13: = Longterm borrowings + shortterm borrowings | P13: 45392 | Q13: 19117 | R13: 1573.9617 | S13: =(Q13-Q12)/Q12 -> -0.0034042205 | T13: =(R13-R12)/R12 -> 0.00093596899
B14: NON-CURRENT LIABILITIES | F14: Cost Of Materials Consumed | G14: 6904.33 | J14: DOL | K14: =K27 / K28 -> 3.2751776 | L14: =_xlfn.FORMULATEXT(K14) -> =K27 / K28 | M14: =Contribution/EBIT | P14: 45394 | Q14: 18788.65 | R14: 1511.113 | S14: =(Q14-Q13)/Q13 -> -0.017175792 | T14: =(R14-R13)/R13 -> -0.039930218
B15: Long Term Borrowings | C15: 1.33 | F15: Purchase Of Stock-In Trade | G15: 3466.15 | J15: DFL | K15: =K28 / K29 -> 1.0215072 | L15: =_xlfn.FORMULATEXT(K15) -> =K28 / K29 | M15: =EBIT/EBT | P15: 45397 | Q15: 18617.65 | R15: 1511.1622 | S15: =(Q15-Q14)/Q14 -> -0.0091012391 | T15: =(R15-R14)/R14 -> 3.2555034e-05
B16: Deferred Tax Liabilities [Net] | C16: 155.06 | F16: Operating And Direct Expenses | G16: 630.26 | J16: DTL | K16: =K14 * K15 -> 3.3456176 | L16: =_xlfn.FORMULATEXT(K16) -> =K14 * K15 | M16: =DOL * DFL | P16: 45398 | Q16: 18695.6 | R16: 1508.7091 | S16: =(Q16-Q15)/Q15 -> 0.0041868451 | T16: =(R16-R15)/R15 -> -0.0016233366
B17: Other Long Term Liabilities | C17: 802.23 | F17: Changes In Inventories Of FGWIP And Stock In Trade | G17: 292.13 | J17: Cost of Debt (Rd) | K17: =G19 / (C15 + C21) -> 0.083800414 | L17: =_xlfn.FORMULATEXT(K17) -> =G19 / (C15 + C21) | M17: =Interest/Total Debt | P17: 45400 | Q17: 18525.75 | R17: 1487.9557 | S17: =(Q17-Q16)/Q16 -> -0.0090850046 | T17: =(R17-R16)/R16 -> -0.013755745
B18: Long Term Provisions | C18: 413.89 | F18: Employee Benefit Expenses | G18: 9429.06 | J18: Cost of Equity (Re) | K18: =K33+K31*(K32-K33) -> 0.10975553 | L18: =_xlfn.FORMULATEXT(K18) -> =K33+K31*(K32-K33) | M18: = RF + Beta(Rm-Rf) | P18: 45401 | Q18: 18404.6 | R18: 1494.2357 | S18: =(Q18-Q17)/Q17 -> -0.0065395674 | T18: =(R18-R17)/R17 -> 0.0042205755
B19: Total Non-Current Liabilities | C19: 1372.51 | F19: Finance Costs | G19: 238.47 | J19: Tax Rate | K19: =G31 / G25 -> 0.12982181 | L19: =_xlfn.FORMULATEXT(K19) -> =G31 / G25 | M19: =Tax/EBT | P19: 45404 | Q19: 18643 | R19: 1511.2112 | S19: =(Q19-Q18)/Q18 -> 0.012953305 | T19: =(R19-R18)/R18 -> 0.011360633
B20: CURRENT LIABILITIES | F20: Depreciation And Amortisation Expenses | G20: 238.47 | J20: Weight of Debt | K20: =K13 / (K13 + C12) -> 0.042784327 | L20: =_xlfn.FORMULATEXT(K20) -> =K13 / (K13 + C12) | M20: =Debt/(Debt+Equity) | P20: 45405 | Q20: 18463.75 | R20: 1456.8013 | S20: =(Q20-Q19)/Q19 -> -0.0096148689 | T20: =(R20-R19)/R19 -> -0.036004175
B21: Short Term Borrowings | C21: 2844.36 | F21: Other Expenses | G21: 14751.79 | J21: Weight of Equity | K21: =C12 / (K13 + C12) -> 0.95721567 | L21: =_xlfn.FORMULATEXT(K21) -> =C12 / (K13 + C12) | M21: =Equity/(Debt+Equity) | P21: 45406 | Q21: 18586.199 | R21: 1457.8806 | S21: =(Q21-Q20)/Q20 -> 0.0066318716 | T21: =(R21-R20)/R20 -> 0.00074090113
B22: Trade Payables | C22: 5653.3 | F22: Total Expenses | G22: 38268.83 | J22: WACC | K22: =K21 * K18 + K20 * K17 -> 0.10864506 | L22: =_xlfn.FORMULATEXT(K22) -> =K21 * K18 + K20 * K17 | M22: =(Equity Weight×Cost of Equity)+(Debt Weight×Cost of Debt) | P22: 45407 | Q22: 18878.15 | R22: 1491.6354 | S22: =(Q22-Q21)/Q21 -> 0.015707955 | T22: =(R22-R21)/R21 -> 0.023153309
B23: Other Current Liabilities | C23: 3129.18 | F23: Profit/Loss Before Exceptional, ExtraOrdinary Items And Tax | G23: 11582.21 | P23: 45408 | Q23: 18994.65 | R23: 1478.2906 | S23: =(Q23-Q22)/Q22 -> 0.0061711554 | T23: =(R23-R22)/R22 -> -0.0089463731
B24: Short Term Provisions | C24: 5357.56 | F24: Exceptional Items | G24: -494.32 | P24: 45411 | Q24: 19096.9 | R24: 1493.0582 | S24: =(Q24-Q23)/Q23 -> 0.0053830946 | T24: =(R24-R23)/R23 -> 0.009989631
B25: Total Current Liabilities | C25: 16984.4 | F25: Profit/Loss Before Tax | G25: 11087.89 | J25: Sale | K25: =G9 -> 47758.45 | L25: =_xlfn.FORMULATEXT(K25) -> =G9 | M25: = Revenue From Operations [Net] | P25: 45412 | Q25: 18970.6 | R25: 1473.924 | S25: =(Q25-Q24)/Q24 -> -0.0066136796 | T25: =(R25-R24)/R24 -> -0.012815493
B26: Total Capital And Liabilities | C26: 85462.88 | F26: Tax Expenses-Continued Operations | J26: Variable Cost | K26: =G14+G15+G17 -> 10662.61 | L26: =_xlfn.FORMULATEXT(K26) -> =G14+G15+G17 | M26: = Cost Of Materials Consumed + Purchase Of Stock-In Trade + Changes In Inventories | P26: 45414 | Q26: 19124.449 | R26: 1490.5071 | S26: =(Q26-Q25)/Q25 -> 0.008109897 | T26: =(R26-R25)/R25 -> 0.011251008
B27: ASSETS | F27: Current Tax | G27: 1989.3 | J27: Contribution | K27: =K25-K26 -> 37095.84 | L27: =_xlfn.FORMULATEXT(K27) -> =K25-K26 | M27: = Contribution =Sales - Variable cost | P27: 45415 | Q27: 19133.4 | R27: 1482.8042 | S27: =(Q27-Q26)/Q26 -> 0.00046804861 | T27: =(R27-R26)/R26 -> -0.0051679599
B28: NON-CURRENT ASSETS | F28: Less: MAT Credit Entitlement | G28: 0 | J28: EBIT | K28: =G25+G19 -> 11326.36 | L28: =_xlfn.FORMULATEXT(K28) -> =G25+G19 | M28: = Profit/Loss Before Tax + Finance Costs | P28: 45418 | Q28: 19203.301 | R28: 1500.4666 | S28: =(Q28-Q27)/Q27 -> 0.0036533177 | T28: =(R28-R27)/R27 -> 0.011911454
B29: Tangible Assets | C29: 10192.32 | F29: Deferred Tax | G29: -549.85 | J29: EBT | K29: =G25 -> 11087.89 | L29: =_xlfn.FORMULATEXT(K29) -> =G25 | M29: = Profit/Loss Before Tax | P29: 45419 | Q29: 18846.301 | R29: 1486.9253 | S29: =(Q29-Q28)/Q28 -> -0.018590554 | T29: =(R29-R28)/R28 -> -0.0090246995
B30: Intangible Assets | C30: 4420.11 | F30: Other Direct Taxes | G30: 0 | P30: 45420 | Q30: 18850.85 | R30: 1493.2054 | S30: =(Q30-Q29)/Q29 -> 0.00024136451 | T30: =(R30-R29)/R29 -> 0.0042235823
B31: Capital Work-In-Progress | C31: 1107.73 | F31: Total Tax Expenses | G31: 1439.45 | J31: Beta | K31: ='SUNPHARMA Beta Calc'!H7 -> 0.97645672 | P31: 45421 | Q31: 18437.051 | R31: 1466.6138 | S31: =(Q31-Q30)/Q30 -> -0.021951203 | T31: =(R31-R30)/R30 -> -0.01780845
B32: Fixed Assets | C32: 19966.31 | F32: Profit/Loss After Tax And Before ExtraOrdinary Items | G32: 9648.44 | J32: Market return (Rm) | K32: ='SUNPHARMA Beta Calc'!H10*252 -> 0.11078641 | P32: 45422 | Q32: 18609.449 | R32: 1478.2906 | S32: =(Q32-Q31)/Q31 -> 0.0093506516 | T32: =(R32-R31)/R31 -> 0.0079617962
B33: Non-Current Investments | C33: 6441.23 | F33: Profit/Loss From Continuing Operations | G33: 9648.44 | J33: Risk Free Rate (Rf) | K33: =6.7/100 -> 0.067 | L33: =6.7/100 | M33: = It is Standard | P33: 45425 | Q33: 18939 | R33: 1496.4436 | S33: =(Q33-Q32)/Q32 -> 0.017708787 | T33: =(R33-R32)/R32 -> 0.012279692
B34: Deferred Tax Assets [Net] | C34: 4103.65 | F34: Profit/Loss For The Period | G34: 9648.44 | P34: 45426 | Q34: 18860.85 | R34: 1516.2645 | S34: =(Q34-Q33)/Q33 -> -0.0041264265 | T34: =(R34-R33)/R33 -> 0.013245352
B35: Long Term Loans And Advances | C35: 0.85 | F35: Minority Interest | G35: -33.65 | P35: 45427 | Q35: 18886.551 | R35: 1498.7493 | S35: =(Q35-Q34)/Q34 -> 0.0013626731 | T35: =(R35-R34)/R34 -> -0.011551585
B36: Other Non-Current Assets | C36: 2876.91 | F36: Consolidated Profit/Loss After MI And Associates | G36: 9576.38 | P36: 45428 | Q36: 18996.15 | R36: 1507.4825 | S36: =(Q36-Q35)/Q35 -> 0.0058030506 | T36: =(R36-R35)/R35 -> 0.005827043
B37: Total Non-Current Assets | C37: 41987.9 | F37: OTHER ADDITIONAL INFORMATION | P37: 45429 | Q37: 18981.6 | R37: 1502.6746 | S37: =(Q37-Q36)/Q36 -> -0.00076598579 | T37: =(R37-R36)/R36 -> -0.0031894123
B38: CURRENT ASSETS | F38: EARNINGS PER SHARE | P38: 45433 | Q38: 19205.199 | R38: 1512.0453 | S38: =(Q38-Q37)/Q37 -> 0.011779809 | T38: =(R38-R37)/R37 -> 0.0062360326
B39: Current Investments | C39: 8584.54 | F39: Basic EPS (Rs.) | G39: 40 | P39: 45434 | Q39: 19317.4 | R39: 1510.4261 | S39: =(Q39-Q38)/Q38 -> 0.005842229 | T39: =(R39-R38)/R38 -> -0.0010708281
B40: Inventories | C40: 9868.29 | F40: Diluted EPS (Rs.) | G40: 40 | P40: 45435 | Q40: 19216.35 | R40: 1467.0552 | S40: =(Q40-Q39)/Q39 -> -0.0052310756 | T40: =(R40-R39)/R39 -> -0.028714394
B41: Trade Receivables | C41: 11249.37 | F41: DIVIDEND AND DIVIDEND PERCENTAGE | P41: 45436 | Q41: 19119.5 | R41: 1458.8129 | S41: =(Q41-Q40)/Q40 -> -0.0050399588 | T41: =(R41-R40)/R40 -> -0.0056182683
B42: Cash And Cash Equivalents | C42: 10520.68 | F42: Equity Share Dividend | G42: 2898.16 | P42: 45439 | Q42: 19111.949 | R42: 1438.5503 | S42: =(Q42-Q41)/Q41 -> -0.00039492566 | T42: =(R42-R41)/R41 -> -0.013889769
B43: Short Term Loans And Advances | C43: 65.02 | F43: Tax On Dividend | G43: 0 | P43: 45440 | Q43: 19215.75 | R43: 1437.4218 | S43: =(Q43-Q42)/Q42 -> 0.005431198 | T43: =(R43-R42)/R42 -> -0.00078449815
B44: OtherCurrentAssets | C44: 3187.08 | P44: 45441 | Q44: 19321.35 | R44: 1451.2081 | S44: =(Q44-Q43)/Q43 -> 0.0054954717 | T44: =(R44-R43)/R43 -> 0.0095910452
B45: Total Current Assets | C45: 43474.98 | P45: 45442 | Q45: 18971 | R45: 1431.7306 | S45: =(Q45-Q44)/Q44 -> -0.018132771 | T45: =(R45-R44)/R44 -> -0.013421603
B46: Total Assets | C46: 85462.88 | P46: 45443 | Q46: 18796.301 | R46: 1432.4175 | S46: =(Q46-Q45)/Q45 -> -0.0092087512 | T46: =(R46-R45)/R45 -> 0.0004797618
B47: OTHER ADDITIONAL INFORMATION | P47: 45446 | Q47: 18864.15 | R47: 1425.7941 | S47: =(Q47-Q46)/Q46 -> 0.0036097321 | T47: =(R47-R46)/R46 -> -0.0046239404
B48: CONTINGENT LIABILITIES, COMMITMENTS | P48: 45447 | Q48: 18603.15 | R48: 1403.0293 | S48: =(Q48-Q47)/Q47 -> -0.013835768 | T48: =(R48-R47)/R47 -> -0.01596638
B49: Contingent Liabilities | C49: 6343.6 | P49: 45448 | Q49: 19281.25 | R49: 1459.4015 | S49: =(Q49-Q48)/Q48 -> 0.036450794 | T49: =(R49-R48)/R48 -> 0.040178913
B50: BONUS DETAILS | P50: 45449 | Q50: 19232.1 | R50: 1445.0754 | S50: =(Q50-Q49)/Q49 -> -0.0025491288 | T50: =(R50-R49)/R49 -> -0.009816387
B51: Bonus Equity Share Capital | C51: 183.81 | P51: 45450 | Q51: 19578 | R51: 1478.5848 | S51: =(Q51-Q50)/Q50 -> 0.017985576 | T51: =(R51-R50)/R50 -> 0.023188685
B52: NON-CURRENT INVESTMENTS | P52: 45453 | Q52: 19774.699 | R52: 1484.7177 | S52: =(Q52-Q51)/Q51 -> 0.010046952 | T52: =(R52-R51)/R51 -> 0.0041477583
B53: Non-Current Investments Quoted Market Value | C53: 0 | P53: 45454 | Q53: 19689.699 | R53: 1471.618 | S53: =(Q53-Q52)/Q52 -> -0.0042984219 | T53: =(R53-R52)/R52 -> -0.0088229633
B54: Non-Current Investments Unquoted Book Value | C54: 0 | P54: 45455 | Q54: 19739.1 | R54: 1478.5848 | S54: =(Q54-Q53)/Q53 -> 0.0025089459 | T54: =(R54-R53)/R53 -> 0.0047341067
B55: CURRENT INVESTMENTS | P55: 45456 | Q55: 19838.5 | R55: 1482.4609 | S55: =(Q55-Q54)/Q54 -> 0.0050357105 | T55: =(R55-R54)/R54 -> 0.0026214922
B56: Current Investments Quoted Market Value | C56: 0 | P56: 45457 | Q56: 19895.65 | R56: 1487.5634 | S56: =(Q56-Q55)/Q55 -> 0.0028807818 | T56: =(R56-R55)/R55 -> 0.0034418559
B57: Current Investments Unquoted Book Value | C57: 0 | P57: 45461 | Q57: 19826.65 | R57: 1492.4203 | S57: =(Q57-Q56)/Q56 -> -0.0034680947 | T57: =(R57-R56)/R56 -> 0.0032650264
P58: 45462 | Q58: 19644.5 | R58: 1475.7885 | S58: =(Q58-Q57)/Q57 -> -0.009187149 | T58: =(R58-R57)/R57 -> -0.011144204
P59: 45463 | Q59: 19544.551 | R59: 1443.4075 | S59: =(Q59-Q58)/Q58 -> -0.0050878983 | T59: =(R59-R58)/R58 -> -0.021941479
P60: 45464 | Q60: 19528.4 | R60: 1439.7277 | S60: =(Q60-Q59)/Q59 -> -0.00082633726 | T60: =(R60-R59)/R59 -> -0.0025493907
P61: 45467 | Q61: 19521.15 | R61: 1466.4667 | S61: =(Q61-Q60)/Q60 -> -0.00037125417 | T61: =(R61-R60)/R60 -> 0.018572272
P62: 45468 | Q62: 19532.301 | R62: 1476.9658 | S62: =(Q62-Q61)/Q61 -> 0.00057119537 | T62: =(R62-R61)/R61 -> 0.0071594846
P63: 45469 | Q63: 19545.35 | R63: 1492.6167 | S63: =(Q63-Q62)/Q62 -> 0.00066806406 | T63: =(R63-R62)/R62 -> 0.010596643
P64: 45470 | Q64: 19514.801 | R64: 1487.8085 | S64: =(Q64-Q63)/Q63 -> -0.0015629717 | T64: =(R64-R63)/R63 -> -0.0032213411
P65: 45471 | Q65: 19731.551 | R65: 1492.3223 | S65: =(Q65-Q64)/Q64 -> 0.011106954 | T65: =(R65-R64)/R64 -> 0.0030338542
P66: 45474 | Q66: 19758.25 | R66: 1491.5863 | S66: =(Q66-Q65)/Q65 -> 0.0013531232 | T66: =(R66-R65)/R65 -> -0.00049316554
P67: 45475 | Q67: 19786.4 | R67: 1495.4623 | S67: =(Q67-Q66)/Q66 -> 0.0014247411 | T67: =(R67-R66)/R66 -> 0.00259856
P68: 45476 | Q68: 19915.301 | R68: 1505.1765 | S68: =(Q68-Q67)/Q67 -> 0.0065145953 | T68: =(R68-R67)/R67 -> 0.0064958064
P69: 45477 | Q69: 20192.6 | R69: 1528.6774 | S69: =(Q69-Q68)/Q68 -> 0.013923909 | T69: =(R69-R68)/R68 -> 0.015613354
... P252: 45744 | Q252: 21137.449 | R252: 1717.8495 | S252: =(Q252-Q251)/Q251 -> -0.0064723948 | T252: =(R252-R251)/R251 -> 0.0018770124

Sheet CIPLA Beta Calc
C2: CIPLA.NS
A3: Price | B3: Close | C3: Close | D3: Return | E3: Return | H3: Covarience(Market/company) | I3: Varience (Market)
A4: Ticker | B4: ^CNXPHARMA | C4: CIPLA.NS | D4: Nifty | E4: Company | H4: =_xlfn.COVARIANCE.S(D7:D252,E7:E252) -> 9.6732111e-05 | I4: =_xlfn.VAR.S(D7:D252) -> 0.00010123143
A5: Date
A6: 45383 | B6: 19207.9 | C6: 1470.343 | H6: Beta
A7: 45384 | B7: 19185.15 | C7: 1461.2678 | D7: =(B7-B6)/B6 -> -0.0011844085 | E7: =(C7-C6)/C6 -> -0.006172162 | H7: =H4/I4 -> 0.95555412
A8: 45385 | B8: 19153.051 | C8: 1443.7058 | D8: =(B8-B7)/B7 -> -0.0016731487 | E8: =(C8-C7)/C7 -> -0.012018339
A9: 45386 | B9: 19125.199 | C9: 1431.9816 | D9: =(B9-B8)/B8 -> -0.001454158 | E9: =(C9-C8)/C8 -> -0.0081209365 | H9: Market Return
A10: 45387 | B10: 19160.75 | C10: 1422.0233 | D10: =(B10-B9)/B9 -> 0.001858845 | E10: =(C10-C9)/C9 -> -0.0069541761 | H10: =AVERAGE(D7:D252) -> 0.00043962859
A11: 45390 | B11: 19218.85 | C11: 1434.8267 | D11: =(B11-B10)/B10 -> 0.00303222 | E11: =(C11-C10)/C10 -> 0.009003611
A12: 45391 | B12: 19182.301 | C12: 1422.9064 | D12: =(B12-B11)/B11 -> -0.0019017178 | E12: =(C12-C11)/C11 -> -0.0083078245
A13: 45392 | B13: 19117 | C13: 1396.0729 | D13: =(B13-B12)/B12 -> -0.0034042205 | E13: =(C13-C12)/C12 -> -0.01885823
A14: 45394 | B14: 18788.65 | C14: 1370.4169 | D14: =(B14-B13)/B13 -> -0.017175792 | E14: =(C14-C13)/C13 -> -0.018377268
A15: 45397 | B15: 18617.65 | C15: 1355.3077 | D15: =(B15-B14)/B14 -> -0.0091012391 | E15: =(C15-C14)/C14 -> -0.011025208
A16: 45398 | B16: 18695.6 | C16: 1349.2247 | D16: =(B16-B15)/B15 -> 0.0041868451 | E16: =(C16-C15)/C15 -> -0.0044882853
A17: 45400 | B17: 18525.75 | C17: 1321.8518 | D17: =(B17-B16)/B16 -> -0.0090850046 | E17: =(C17-C16)/C16 -> -0.020287891
A18: 45401 | B18: 18404.6 | C18: 1320.3311 | D18: =(B18-B17)/B17 -> -0.0065395674 | E18: =(C18-C17)/C17 -> -0.0011504708
A19: 45404 | B19: 18643 | C19: 1329.2592 | D19: =(B19-B18)/B18 -> 0.012953305 | E19: =(C19-C18)/C18 -> 0.0067620167
A20: 45405 | B20: 18463.75 | C20: 1321.2631 | D20: =(B20-B19)/B19 -> -0.0096148689 | E20: =(C20-C19)/C19 -> -0.0060154513
A21: 45406 | B21: 18586.199 | C21: 1371.7904 | D21: =(B21-B20)/B20 -> 0.0066318716 | E21: =(C21-C20)/C20 -> 0.038241699
A22: 45407 | B22: 18878.15 | C22: 1379.6393 | D22: =(B22-B21)/B21 -> 0.015707955 | E22: =(C22-C21)/C21 -> 0.0057216299
... A252: 45744 | B252: 21137.449 | C252: 1426.9567 | D252: =(B252-B251)/B251 -> -0.0064723948 | E252: =(C252-C251)/C251 -> -0.027446271

Sheet CIPLA 
C2: CIPLA | P2: CIPLA.NS
P3: Price | Q3: Close | R3: Close | S3: Return | T3: Return | W3: Covarience(Market/company) | X3: Varience (Market)
B4: Balance Sheet of Cipla (in Rs. Cr.) | C4: 46105 | F4: Profit & Loss account of Cipla (in Rs. Cr.) | G4: 46105 | P4: Ticker | Q4: ^CNXPHARMA | R4: CIPLA.NS | S4: Nifty | T4: Company | W4: =_xlfn.COVARIANCE.S(S7:S252,T7:T252) -> 9.6732111e-05 | X4: =_xlfn.VAR.S(S7:S252) -> 0.00010123143
C5: 12 mths | G5: 12 mths | P5: Date
B6: EQUITIES AND LIABILITIES | F6: INCOME | P6: 45383 | Q6: 19207.9 | R6: 1470.343 | W6: Beta
B7: SHAREHOLDER'S FUNDS | F7: Revenue From Operations [Gross] | G7: 25446.63 | P7: 45384 | Q7: 19185.15 | R7: 1461.2678 | S7: =(Q7-Q6)/Q6 -> -0.0011844085 | T7: =(R7-R6)/R6 -> -0.006172162 | W7: =W4/X4 -> 0.95555412
B8: Equity Share Capital | C8: 161.47 | F8: Less: Excise/Sevice Tax/Other Levies | G8: 0 | P8: 45385 | Q8: 19153.051 | R8: 1443.7058 | S8: =(Q8-Q7)/Q7 -> -0.0016731487 | T8: =(R8-R7)/R7 -> -0.012018339
B9: Total Share Capital | C9: 161.47 | F9: Revenue From Operations [Net] | G9: 25446.63 | P9: 45386 | Q9: 19125.199 | R9: 1431.9816 | S9: =(Q9-Q8)/Q8 -> -0.001454158 | T9: =(R9-R8)/R8 -> -0.0081209365 | W9: Market Return
B10: Reserves and Surplus | C10: 26544.96 | F10: Total Operating Revenues | G10: 25774.09 | P10: 45387 | Q10: 19160.75 | R10: 1422.0233 | S10: =(Q10-Q9)/Q9 -> 0.001858845 | T10: =(R10-R9)/R9 -> -0.0069541761 | W10: =AVERAGE(S7:S252) -> 0.00043962859
B11: Total Reserves and Surplus | C11: 26544.96 | F11: Other Income | G11: 746.57 | P11: 45390 | Q11: 19218.85 | R11: 1434.8267 | S11: =(Q11-Q10)/Q10 -> 0.00303222 | T11: =(R11-R10)/R10 -> 0.009003611
B12: Total Shareholders Funds | C12: 26706.43 | F12: Total Revenue | G12: 26520.66 | P12: 45391 | Q12: 19182.301 | R12: 1422.9064 | S12: =(Q12-Q11)/Q11 -> -0.0019017178 | T12: =(R12-R11)/R11 -> -0.0083078245
B13: Minority Interest | C13: 95.9 | F13: EXPENSES | J13: Total Debt | K13: =C15 + C21 -> 247.02 | L13: =_xlfn.FORMULATEXT(K13) -> =C15 + C21 | M13: = Longterm borrowings + shortterm borrowings | P13: 45392 | Q13: 19117 | R13: 1396.0729 | S13: =(Q13-Q12)/Q12 -> -0.0034042205 | T13: =(R13-R12)/R12 -> -0.01885823
B14: NON-CURRENT LIABILITIES | F14: Cost Of Materials Consumed | G14: 5220.51 | J14: DOL | K14: =K27 / K28 -> 2.8708031 | L14: =_xlfn.FORMULATEXT(K14) -> =K27 / K28 | M14: =Contribution/EBIT | P14: 45394 | Q14: 18788.65 | R14: 1370.4169 | S14: =(Q14-Q13)/Q13 -> -0.017175792 | T14: =(R14-R13)/R13 -> -0.018377268
B15: Long Term Borrowings | C15: 0 | F15: Purchase Of Stock-In Trade | G15: 3536.03 | J15: DFL | K15: =K28 / K29 -> 1.0157632 | L15: =_xlfn.FORMULATEXT(K15) -> =K28 / K29 | M15: =EBIT/EBT | P15: 45397 | Q15: 18617.65 | R15: 1355.3077 | S15: =(Q15-Q14)/Q14 -> -0.0091012391 | T15: =(R15-R14)/R14 -> -0.011025208
B16: Deferred Tax Liabilities [Net] | C16: 185.29 | F16: Operating And Direct Expenses | G16: 640.62 | J16: DTL | K16: =K14 * K15 -> 2.9160561 | L16: =_xlfn.FORMULATEXT(K16) -> =K14 * K15 | M16: =DOL * DFL | P16: 45398 | Q16: 18695.6 | R16: 1349.2247 | S16: =(Q16-Q15)/Q15 -> 0.0041868451 | T16: =(R16-R15)/R15 -> -0.0044882853
B17: Other Long Term Liabilities | C17: 355.17 | F17: Changes In Inventories Of FGWIP And Stock In Trade | G17: 63.03 | J17: Cost of Debt (Rd) | K17: =G19 / (C15 + C21) -> 0.36385718 | L17: =_xlfn.FORMULATEXT(K17) -> =G19 / (C15 + C21) | M17: =Interest/Total Debt | P17: 45400 | Q17: 18525.75 | R17: 1321.8518 | S17: =(Q17-Q16)/Q16 -> -0.0090850046 | T17: =(R17-R16)/R16 -> -0.020287891
B18: Long Term Provisions | C18: 129.26 | F18: Employee Benefit Expenses | G18: 4310.04 | J18: Cost of Equity (Re) | K18: =K33+K31*(K32-K33) -> 0.10884028 | L18: =_xlfn.FORMULATEXT(K18) -> =K33+K31*(K32-K33) | M18: = RF + Beta(Rm-Rf) | P18: 45401 | Q18: 18404.6 | R18: 1320.3311 | S18: =(Q18-Q17)/Q17 -> -0.0065395674 | T18: =(R18-R17)/R17 -> -0.0011504708
B19: Total Non-Current Liabilities | C19: 669.72 | F19: Finance Costs | G19: 89.88 | J19: Tax Rate | K19: =G31 / G25 -> 0.27124117 | L19: =_xlfn.FORMULATEXT(K19) -> =G31 / G25 | M19: =Tax/EBT | P19: 45404 | Q19: 18643 | R19: 1329.2592 | S19: =(Q19-Q18)/Q18 -> 0.012953305 | T19: =(R19-R18)/R18 -> 0.0067620167
B20: CURRENT LIABILITIES | F20: Depreciation And Amortisation Expenses | G20: 1051.02 | J20: Weight of Debt | K20: =K13 / (K13 + C12) -> 0.0091646895 | L20: =_xlfn.FORMULATEXT(K20) -> =K13 / (K13 + C12) | M20: =Debt/(Debt+Equity) | P20: 45405 | Q20: 18463.75 | R20: 1321.2631 | S20: =(Q20-Q19)/Q19 -> -0.0096148689 | T20: =(R20-R19)/R19 -> -0.0060154513
B21: Short Term Borrowings | C21: 247.02 | F21: Other Expenses | G21: 5712.81 | J21: Weight of Equity | K21: =C12 / (K13 + C12) -> 0.99083531 | L21: =_xlfn.FORMULATEXT(K21) -> =C12 / (K13 + C12) | M21: =Equity/(Debt+Equity) | P21: 45406 | Q21: 18586.199 | R21: 1371.7904 | S21: =(Q21-Q20)/Q20 -> 0.0066318716 | T21: =(R21-R20)/R20 -> 0.038241699
B22: Trade Payables | C22: 2473.98 | F22: Total Expenses | G22: 20623.94 | J22: WACC | K22: =K21 * K18 + K20 * K17 -> 0.11117743 | L22: =_xlfn.FORMULATEXT(K22) -> =K21 * K18 + K20 * K17 | M22: =(Equity Weight×Cost of Equity)+(Debt Weight×Cost of Debt) | P22: 45407 | Q22: 18878.15 | R22: 1379.6393 | S22: =(Q22-Q21)/Q21 -> 0.015707955 | T22: =(R22-R21)/R21 -> 0.0057216299
B23: Other Current Liabilities | C23: 913.01 | F23: Profit/Loss Before Exceptional, ExtraOrdinary Items And Tax | G23: 5896.72 | P23: 45408 | Q23: 18994.65 | R23: 1382.5336 | S23: =(Q23-Q22)/Q22 -> 0.0061711554 | T23: =(R23-R22)/R22 -> 0.0020978579
B24: Short Term Provisions | C24: 1611.76 | F24: Exceptional Items | G24: -194.82 | P24: 45411 | Q24: 19096.9 | R24: 1381.4053 | S24: =(Q24-Q23)/Q23 -> 0.0053830946 | T24: =(R24-R23)/R23 -> -0.00081610742
B25: Total Current Liabilities | C25: 5245.77 | F25: Profit/Loss Before Tax | G25: 5701.9 | J25: Sale | K25: =G9 -> 25446.63 | L25: =_xlfn.FORMULATEXT(K25) -> =G9 | M25: = Revenue From Operations [Net] | P25: 45412 | Q25: 18970.6 | R25: 1373.5564 | S25: =(Q25-Q24)/Q24 -> -0.0066136796 | T25: =(R25-R24)/R24 -> -0.0056818061
B26: Total Capital And Liabilities | C26: 32717.82 | F26: Tax Expenses-Continued Operations | J26: Variable Cost | K26: =G14+G15+G17 -> 8819.57 | L26: =_xlfn.FORMULATEXT(K26) -> =G14+G15+G17 | M26: = Cost Of Materials Consumed + Purchase Of Stock-In Trade + Changes In Inventories | P26: 45414 | Q26: 19124.449 | R26: 1393.2278 | S26: =(Q26-Q25)/Q25 -> 0.008109897 | T26: =(R26-R25)/R25 -> 0.014321499
B27: ASSETS | F27: Current Tax | G27: 1696.84 | J27: Contribution | K27: =K25-K26 -> 16627.06 | L27: =_xlfn.FORMULATEXT(K27) -> =K25-K26 | M27: = Contribution =Sales - Variable cost | P27: 45415 | Q27: 19133.4 | R27: 1397.8389 | S27: =(Q27-Q26)/Q26 -> 0.00046804861 | T27: =(R27-R26)/R26 -> 0.0033096411
B28: NON-CURRENT ASSETS | F28: Less: MAT Credit Entitlement | G28: 0 | J28: EBIT | K28: =G25+G19 -> 5791.78 | L28: =_xlfn.FORMULATEXT(K28) -> =G25+G19 | M28: = Profit/Loss Before Tax + Finance Costs | P28: 45418 | Q28: 19203.301 | R28: 1396.5144 | S28: =(Q28-Q27)/Q27 -> 0.0036533177 | T28: =(R28-R27)/R27 -> -0.00094750756
B29: Tangible Assets | C29: 5182.58 | F29: Deferred Tax | G29: -150.25 | J29: EBT | K29: =G25 -> 5701.9 | L29: =_xlfn.FORMULATEXT(K29) -> =G25 | M29: = Profit/Loss Before Tax | P29: 45419 | Q29: 18846.301 | R29: 1360.998 | S29: =(Q29-Q28)/Q28 -> -0.018590554 | T29: =(R29-R28)/R28 -> -0.025432145
B30: Intangible Assets | C30: 1312.6 | F30: Other Direct Taxes | G30: 0 | P30: 45420 | Q30: 18850.85 | R30: 1358.5945 | S30: =(Q30-Q29)/Q29 -> 0.00024136451 | T30: =(R30-R29)/R29 -> -0.0017660308
B31: Capital Work-In-Progress | C31: 864.32 | F31: Total Tax Expenses | G31: 1546.59 | J31: Beta | K31: ='CIPLA Beta Calc'!H7 -> 0.95555412 | P31: 45421 | Q31: 18437.051 | R31: 1333.1346 | S31: =(Q31-Q30)/Q30 -> -0.021951203 | T31: =(R31-R30)/R30 -> -0.018739837
B32: Fixed Assets | C32: 7647.9 | F32: Profit/Loss After Tax And Before ExtraOrdinary Items | G32: 4155.31 | J32: Market return (Rm) | K32: ='CIPLA Beta Calc'!H10*252 -> 0.11078641 | P32: 45422 | Q32: 18609.449 | R32: 1314.2482 | S32: =(Q32-Q31)/Q31 -> 0.0093506516 | T32: =(R32-R31)/R31 -> -0.014166967
B33: Non-Current Investments | C33: 642.21 | F33: Profit/Loss From Continuing Operations | G33: 4155.31 | J33: Risk Free Rate (Rf) | K33: =6.7/100 -> 0.067 | L33: =6.7/100 | M33: = It is Standard | P33: 45425 | Q33: 18939 | R33: 1387.9297 | S33: =(Q33-Q32)/Q32 -> 0.017708787 | T33: =(R33-R32)/R32 -> 0.056063627
B34: Deferred Tax Assets [Net] | C34: 587.8 | F34: Profit/Loss For The Period | G34: 4155.31 | P34: 45426 | Q34: 18860.85 | R34: 1331.7119 | S34: =(Q34-Q33)/Q33 -> -0.0041264265 | T34: =(R34-R33)/R33 -> -0.04050477
B35: Long Term Loans And Advances | C35: 16.98 | F35: Minority Interest | G35: -32.17 | P35: 45427 | Q35: 18886.551 | R35: 1380.1298 | S35: =(Q35-Q34)/Q34 -> 0.0013626731 | T35: =(R35-R34)/R34 -> 0.036357598
B36: Other Non-Current Assets | C36: 1269.48 | F36: Consolidated Profit/Loss After MI And Associates | G36: 4121.55 | P36: 45428 | Q36: 18996.15 | R36: 1394.2578 | S36: =(Q36-Q35)/Q35 -> 0.0058030506 | T36: =(R36-R35)/R35 -> 0.010236756
B37: Total Non-Current Assets | C37: 13276.41 | F37: OTHER ADDITIONAL INFORMATION | P37: 45429 | Q37: 18981.6 | R37: 1372.6244 | S37: =(Q37-Q36)/Q36 -> -0.00076598579 | T37: =(R37-R36)/R36 -> -0.015516085
B38: CURRENT ASSETS | F38: EARNINGS PER SHARE | P38: 45433 | Q38: 19205.199 | R38: 1415.0574 | S38: =(Q38-Q37)/Q37 -> 0.011779809 | T38: =(R38-R37)/R37 -> 0.030913762
B39: Current Investments | C39: 4807.01 | F39: Basic EPS (Rs.) | G39: 51 | P39: 45434 | Q39: 19317.4 | R39: 1454.3019 | S39: =(Q39-Q38)/Q38 -> 0.005842229 | T39: =(R39-R38)/R38 -> 0.027733509
B40: Inventories | C40: 5237.95 | F40: Diluted EPS (Rs.) | G40: 51 | P40: 45435 | Q40: 19216.35 | R40: 1461.0225 | S40: =(Q40-Q39)/Q39 -> -0.0052310756 | T40: =(R40-R39)/R39 -> 0.0046211733
B41: Trade Receivables | C41: 4770.66 | F41: DIVIDEND AND DIVIDEND PERCENTAGE | P41: 45436 | Q41: 19119.5 | R41: 1458.3734 | S41: =(Q41-Q40)/Q40 -> -0.0050399588 | T41: =(R41-R40)/R40 -> -0.0018131466
B42: Cash And Cash Equivalents | C42: 874.97 | F42: Equity Share Dividend | G42: 686.17 | P42: 45439 | Q42: 19111.949 | R42: 1450.7209 | S42: =(Q42-Q41)/Q41 -> -0.00039492566 | T42: =(R42-R41)/R41 -> -0.0052472609
B43: Short Term Loans And Advances | C43: 0.24 | F43: Tax On Dividend | G43: 0 | P43: 45440 | Q43: 19215.75 | R43: 1451.5056 | S43: =(Q43-Q42)/Q42 -> 0.005431198 | T43: =(R43-R42)/R42 -> 0.00054088139
B44: OtherCurrentAssets | C44: 3750.58 | P44: 45441 | Q44: 19321.35 | R44: 1465.3394 | S44: =(Q44-Q43)/Q43 -> 0.0054954717 | T44: =(R44-R43)/R43 -> 0.0095306143
B45: Total Current Assets | C45: 19441.41 | P45: 45442 | Q45: 18971 | R45: 1438.8983 | S45: =(Q45-Q44)/Q44 -> -0.018132771 | T45: =(R45-R44)/R44 -> -0.018044312
B46: Total Assets | C46: 32717.82 | P46: 45443 | Q46: 18796.301 | R46: 1419.8649 | S46: =(Q46-Q45)/Q45 -> -0.0092087512 | T46: =(R46-R45)/R45 -> -0.013227792
B47: OTHER ADDITIONAL INFORMATION | P47: 45446 | Q47: 18864.15 | R47: 1424.9176 | S47: =(Q47-Q46)/Q46 -> 0.0036097321 | T47: =(R47-R46)/R46 -> 0.0035586023
B48: CONTINGENT LIABILITIES, COMMITMENTS | P48: 45447 | Q48: 18603.15 | R48: 1434.9249 | S48: =(Q48-Q47)/Q47 -> -0.013835768 | T48: =(R48-R47)/R47 -> 0.0070230898
B49: Contingent Liabilities | C49: 4629.56 | P49: 45448 | Q49: 19281.25 | R49: 1468.675 | S49: =(Q49-Q48)/Q48 -> 0.036450794 | T49: =(R49-R48)/R48 -> 0.023520479
B50: BONUS DETAILS | P50: 45449 | Q50: 19232.1 | R50: 1449.1019 | S50: =(Q50-Q49)/Q49 -> -0.0025491288 | T50: =(R50-R49)/R49 -> -0.01332706
B51: Bonus Equity Share Capital | C51: 151.66 | P51: 45450 | Q51: 19578 | R51: 1468.9695 | S51: =(Q51-Q50)/Q50 -> 0.017985576 | T51: =(R51-R50)/R50 -> 0.013710253
B52: NON-CURRENT INVESTMENTS | P52: 45453 | Q52: 19774.699 | R52: 1505.2706 | S52: =(Q52-Q51)/Q51 -> 0.010046952 | T52: =(R52-R51)/R51 -> 0.024711982
B53: Non-Current Investments Quoted Market Value | C53: 0 | P53: 45454 | Q53: 19689.699 | R53: 1501.3462 | S53: =(Q53-Q52)/Q52 -> -0.0042984219 | T53: =(R53-R52)/R52 -> -0.0026071315
B54: Non-Current Investments Unquoted Book Value | C54: 512.16 | P54: 45455 | Q54: 19739.1 | R54: 1511.8441 | S54: =(Q54-Q53)/Q53 -> 0.0025089459 | T54: =(R54-R53)/R53 -> 0.0069923412
B55: CURRENT INVESTMENTS | P55: 45456 | Q55: 19838.5 | R55: 1515.3762 | S55: =(Q55-Q54)/Q54 -> 0.0050357105 | T55: =(R55-R54)/R54 -> 0.0023362888
B56: Current Investments Quoted Market Value | C56: 0 | P56: 45457 | Q56: 19895.65 | R56: 1535.1945 | S56: =(Q56-Q55)/Q55 -> 0.0028807818 | T56: =(R56-R55)/R55 -> 0.013078097
B57: Current Investments Unquoted Book Value | C57: 4807.01 | P57: 45461 | Q57: 19826.65 | R57: 1545.0547 | S57: =(Q57-Q56)/Q56 -> -0.0034680947 | T57: =(R57-R56)/R56 -> 0.0064227886
P58: 45462 | Q58: 19644.5 | R58: 1530.338 | S58: =(Q58-Q57)/Q57 -> -0.009187149 | T58: =(R58-R57)/R57 -> -0.0095250187
P59: 45463 | Q59: 19544.551 | R59: 1515.6704 | S59: =(Q59-Q58)/Q58 -> -0.0050878983 | T59: =(R59-R58)/R58 -> -0.0095845509
P60: 45464 | Q60: 19528.4 | R60: 1512.4327 | S60: =(Q60-Q59)/Q59 -> -0.00082633726 | T60: =(R60-R59)/R59 -> -0.0021361312
P61: 45467 | Q61: 19521.15 | R61: 1475.9845 | S61: =(Q61-Q60)/Q60 -> -0.00037125417 | T61: =(R61-R60)/R60 -> -0.024099083
P62: 45468 | Q62: 19532.301 | R62: 1471.3732 | S62: =(Q62-Q61)/Q61 -> 0.00057119537 | T62: =(R62-R61)/R61 -> -0.0031242389
P63: 45469 | Q63: 19545.35 | R63: 1451.1624 | S63: =(Q63-Q62)/Q62 -> 0.00066806406 | T63: =(R63-R62)/R62 -> -0.013736023
P64: 45470 | Q64: 19514.801 | R64: 1452.9283 | S64: =(Q64-Q63)/Q63 -> -0.0015629717 | T64: =(R64-R63)/R63 -> 0.0012169494
P65: 45471 | Q65: 19731.551 | R65: 1452.8302 | S65: =(Q65-Q64)/Q64 -> 0.011106954 | T65: =(R65-R64)/R64 -> -6.7549464e-05
P66: 45474 | Q66: 19758.25 | R66: 1451.1624 | S66: =(Q66-Q65)/Q65 -> 0.0013531232 | T66: =(R66-R65)/R65 -> -0.0011479984
P67: 45475 | Q67: 19786.4 | R67: 1460.532 | S67: =(Q67-Q66)/Q66 -> 0.0014247411 | T67: =(R67-R66)/R66 -> 0.0064566372
P68: 45476 | Q68: 19915.301 | R68: 1455.7245 | S68: =(Q68-Q67)/Q67 -> 0.0065145953 | T68: =(R68-R67)/R67 -> -0.0032916055
P69: 45477 | Q69: 20192.6 | R69: 1452.7811 | S69: =(Q69-Q68)/Q68 -> 0.013923909 | T69: =(R69-R68)/R68 -> -0.0020219206
... P252: 45744 | Q252: 21137.449 | R252: 1426.9567 | S252: =(Q252-Q251)/Q251 -> -0.0064723948 | T252: =(R252-R251)/R251 -> -0.027446271

Sheet DR. REDDY Beta Calc
C2: DRREDDY.NS
A3: Price | B3: Close | C3: Close | D3: Return | E3: Return | H3: Covarience(Market/company) | I3: Variance (Market)
A4: Ticker | B4: ^CNXPHARMA | C4: DRREDDY.NS | D4: Nifty | E4: Company | H4: =_xlfn.COVARIANCE.S(D7:D252,E7:E252) -> 8.2296476e-05 | I4: =_xlfn.VAR.S(D7:D252) -> 0.00010123143
A5: Date
A6: 45383 | B6: 19207.9 | C6: 1234.8792 | H6: Beta
A7: 45384 | B7: 19185.15 | C7: 1232.3502 | D7: =(B7-B6)/B6 -> -0.0011844085 | E7: =(C7-C6)/C6 -> -0.0020479175 | H7: =H4/I4 -> 0.81295379
A8: 45385 | B8: 19153.051 | C8: 1209.9952 | D8: =(B8-B7)/B7 -> -0.0016731487 | E8: =(C8-C7)/C7 -> -0.01814012
A9: 45386 | B9: 19125.199 | C9: 1213.5713 | D9: =(B9-B8)/B8 -> -0.001454158 | E9: =(C9-C8)/C8 -> 0.0029554247 | H9: Market Return
A10: 45387 | B10: 19160.75 | C10: 1220.8418 | D10: =(B10-B9)/B9 -> 0.001858845 | E10: =(C10-C9)/C9 -> 0.0059910018 | H10: =AVERAGE(D7:D252) -> 0.00043962859
A11: 45390 | B11: 19218.85 | C11: 1219.9034 | D11: =(B11-B10)/B10 -> 0.00303222 | E11: =(C11-C10)/C10 -> -0.00076861269
A12: 45391 | B12: 19182.301 | C12: 1218.5895 | D12: =(B12-B11)/B11 -> -0.0019017178 | E12: =(C12-C11)/C11 -> -0.0010771056
A13: 45392 | B13: 19117 | C13: 1216.6138 | D13: =(B13-B12)/B12 -> -0.0034042205 | E13: =(C13-C12)/C12 -> -0.0016213073
A14: 45394 | B14: 18788.65 | C14: 1201.9839 | D14: =(B14-B13)/B13 -> -0.017175792 | E14: =(C14-C13)/C13 -> -0.012025084
A15: 45397 | B15: 18617.65 | C15: 1187.5613 | D15: =(B15-B14)/B14 -> -0.0091012391 | E15: =(C15-C14)/C14 -> -0.011999002
A16: 45398 | B16: 18695.6 | C16: 1195.3652 | D16: =(B16-B15)/B15 -> 0.0041868451 | E16: =(C16-C15)/C15 -> 0.0065714125
A17: 45400 | B17: 18525.75 | C17: 1176.9519 | D17: =(B17-B16)/B16 -> -0.0090850046 | E17: =(C17-C16)/C16 -> -0.015403936
A18: 45401 | B18: 18404.6 | C18: 1174.1265 | D18: =(B18-B17)/B17 -> -0.0065395674 | E18: =(C18-C17)/C17 -> -0.0024006414
A19: 45404 | B19: 18643 | C19: 1188.5985 | D19: =(B19-B18)/B18 -> 0.012953305 | E19: =(C19-C18)/C18 -> 0.012325798
A20: 45405 | B20: 18463.75 | C20: 1175.954 | D20: =(B20-B19)/B19 -> -0.0096148689 | E20: =(C20-C19)/C19 -> -0.010638185
A21: 45406 | B21: 18586.199 | C21: 1175.6973 | D21: =(B21-B20)/B20 -> 0.0066318716 | E21: =(C21-C20)/C20 -> -0.00021830265
A22: 45407 | B22: 18878.15 | C22: 1228.6359 | D22: =(B22-B21)/B21 -> 0.015707955 | E22: =(C22-C21)/C21 -> 0.045027406
... A252: 45744 | B252: 21137.449 | C252: 1136.989 | D252: =(B252-B251)/B251 -> -0.0064723948 | E252: =(C252-C251)/C251 -> -0.015487899

Sheet Dr. Reddy's Laboratories
C2: Dr. Reddy's Laboratories | P2: DRREDDY.NS
P3: Price | Q3: Close | R3: Close | S3: Return | T3: Return | W3: Covarience(Market/company) | X3: Variance (Market)
B4: Balance Sheet of Dr Reddys Laboratories (in Rs. Cr.) | C4: 46105 | F4: Profit & Loss account of Dr Reddys Laboratories (in Rs. Cr.) | G4: 46105 | P4: Ticker | Q4: ^CNXPHARMA | R4: DRREDDY.NS | S4: Nifty | T4: Company | W4: =_xlfn.COVARIANCE.S(S7:S252,T7:T252) -> 8.2296476e-05 | X4: =_xlfn.VAR.S(S7:S252) -> 0.00010123143
C5: 12 mths | G5: 12 mths | P5: Date
B6: EQUITIES AND LIABILITIES | F6: INCOME | P6: 45383 | Q6: 19207.9 | R6: 1234.8792 | W6: Beta
B7: SHAREHOLDER'S FUNDS | F7: Revenue From Operations [Gross] | G7: 27916.4 | P7: 45384 | Q7: 19185.15 | R7: 1232.3502 | S7: =(Q7-Q6)/Q6 -> -0.0011844085 | T7: =(R7-R6)/R6 -> -0.0020479175 | W7: =W4/X4 -> 0.81295379
B8: Equity Share Capital | C8: 83.4 | F8: Less: Excise/Sevice Tax/Other Levies | G8: 0 | P8: 45385 | Q8: 19153.051 | R8: 1209.9952 | S8: =(Q8-Q7)/Q7 -> -0.0016731487 | T8: =(R8-R7)/R7 -> -0.01814012
B9: Total Share Capital | C9: 83.4 | F9: Revenue From Operations [Net] | G9: 27916.4 | P9: 45386 | Q9: 19125.199 | R9: 1213.5713 | S9: =(Q9-Q8)/Q8 -> -0.001454158 | T9: =(R9-R8)/R8 -> 0.0029554247 | W9: Market Return
B10: Reserves and Surplus | C10: 28171.4 | F10: Total Operating Revenues | G10: 28011.1 | P10: 45387 | Q10: 19160.75 | R10: 1220.8418 | S10: =(Q10-Q9)/Q9 -> 0.001858845 | T10: =(R10-R9)/R9 -> 0.0059910018 | W10: =AVERAGE(S7:S252) -> 0.00043962859
B11: Total Reserves and Surplus | C11: 28171.4 | F11: Other Income | G11: 894.3 | P11: 45390 | Q11: 19218.85 | R11: 1219.9034 | S11: =(Q11-Q10)/Q10 -> 0.00303222 | T11: =(R11-R10)/R10 -> -0.00076861269
B12: Total Shareholders Funds | C12: 28254.8 | F12: Total Revenue | G12: 28905.4 | P12: 45391 | Q12: 19182.301 | R12: 1218.5895 | S12: =(Q12-Q11)/Q11 -> -0.0019017178 | T12: =(R12-R11)/R11 -> -0.0010771056
B13: Minority Interest | C13: 0 | F13: EXPENSES | J13: Total Debt | K13: =C15 + C21 -> 1652.3 | L13: =_xlfn.FORMULATEXT(K13) -> =C15 + C21 | M13: = Longterm borrowings + shortterm borrowings | P13: 45392 | Q13: 19117 | R13: 1216.6138 | S13: =(Q13-Q12)/Q12 -> -0.0034042205 | T13: =(R13-R12)/R12 -> -0.0016213073
B14: NON-CURRENT LIABILITIES | F14: Cost Of Materials Consumed | G14: 4490.1 | J14: DOL | K14: =K27 / K28 -> 2.6786229 | L14: =_xlfn.FORMULATEXT(K14) -> =K27 / K28 | M14: =Contribution/EBIT | P14: 45394 | Q14: 18788.65 | R14: 1201.9839 | S14: =(Q14-Q13)/Q13 -> -0.017175792 | T14: =(R14-R13)/R13 -> -0.012025084
B15: Long Term Borrowings | C15: 380 | F15: Purchase Of Stock-In Trade | G15: 4399.1 | J15: DFL | K15: =K28 / K29 -> 1.0238092 | L15: =_xlfn.FORMULATEXT(K15) -> =K28 / K29 | M15: =EBIT/EBT | P15: 45397 | Q15: 18617.65 | R15: 1187.5613 | S15: =(Q15-Q14)/Q14 -> -0.0091012391 | T15: =(R15-R14)/R14 -> -0.011999002
B16: Deferred Tax Liabilities [Net] | C16: 84.1 | F16: Operating And Direct Expenses | G16: 0 | J16: DTL | K16: =K14 * K15 -> 2.7423987 | L16: =_xlfn.FORMULATEXT(K16) -> =K14 * K15 | M16: =DOL * DFL | P16: 45398 | Q16: 18695.6 | R16: 1195.3652 | S16: =(Q16-Q15)/Q15 -> 0.0041868451 | T16: =(R16-R15)/R15 -> 0.0065714125
B17: Other Long Term Liabilities | C17: 533 | F17: Changes In Inventories Of FGWIP And Stock In Trade | G17: -680.5 | J17: Cost of Debt (Rd) | K17: =G19 / (C15 + C21) -> 0.10355262 | L17: =_xlfn.FORMULATEXT(K17) -> =G19 / (C15 + C21) | M17: =Interest/Total Debt | P17: 45400 | Q17: 18525.75 | R17: 1176.9519 | S17: =(Q17-Q16)/Q16 -> -0.0090850046 | T17: =(R17-R16)/R16 -> -0.015403936
B18: Long Term Provisions | C18: 23.9 | F18: Employee Benefit Expenses | G18: 5030.1 | J18: Cost of Equity (Re) | K18: =K33+K31*(K32-K33) -> 0.10259632 | L18: =_xlfn.FORMULATEXT(K18) -> =K33+K31*(K32-K33) | M18: = RF + Beta(Rm-Rf) | P18: 45401 | Q18: 18404.6 | R18: 1174.1265 | S18: =(Q18-Q17)/Q17 -> -0.0065395674 | T18: =(R18-R17)/R17 -> -0.0024006414
B19: Total Non-Current Liabilities | C19: 1021 | F19: Finance Costs | G19: 171.1 | J19: Tax Rate | K19: =G31 / G25 -> 0.22586032 | L19: =_xlfn.FORMULATEXT(K19) -> =G31 / G25 | M19: =Tax/EBT | P19: 45404 | Q19: 18643 | R19: 1188.5985 | S19: =(Q19-Q18)/Q18 -> 0.012953305 | T19: =(R19-R18)/R18 -> 0.012325798
B20: CURRENT LIABILITIES | F20: Depreciation And Amortisation Expenses | G20: 1470 | J20: Weight of Debt | K20: =K13 / (K13 + C12) -> 0.055247751 | L20: =_xlfn.FORMULATEXT(K20) -> =K13 / (K13 + C12) | M20: =Debt/(Debt+Equity) | P20: 45405 | Q20: 18463.75 | R20: 1175.954 | S20: =(Q20-Q19)/Q19 -> -0.0096148689 | T20: =(R20-R19)/R19 -> -0.010638185
B21: Short Term Borrowings | C21: 1272.3 | F21: Other Expenses | G21: 6838.9 | J21: Weight of Equity | K21: =C12 / (K13 + C12) -> 0.94475225 | L21: =_xlfn.FORMULATEXT(K21) -> =C12 / (K13 + C12) | M21: =Equity/(Debt+Equity) | P21: 45406 | Q21: 18586.199 | R21: 1175.6973 | S21: =(Q21-Q20)/Q20 -> 0.0066318716 | T21: =(R21-R20)/R20 -> -0.00021830265
B22: Trade Payables | C22: 2614.4 | F22: Total Expenses | G22: 21719.1 | J22: WACC | K22: =K21 * K18 + K20 * K17 -> 0.10264916 | L22: =_xlfn.FORMULATEXT(K22) -> =K21 * K18 + K20 * K17 | M22: =(Equity Weight×Cost of Equity)+(Debt Weight×Cost of Debt) | P22: 45407 | Q22: 18878.15 | R22: 1228.6359 | S22: =(Q22-Q21)/Q21 -> 0.015707955 | T22: =(R22-R21)/R21 -> 0.045027406
B23: Other Current Liabilities | C23: 5009.3 | F23: Profit/Loss Before Exceptional, ExtraOrdinary Items And Tax | G23: 7186.3 | P23: 45408 | Q23: 18994.65 | R23: 1235.225 | S23: =(Q23-Q22)/Q22 -> 0.0061711554 | T23: =(R23-R22)/R22 -> 0.0053629489
B24: Short Term Provisions | C24: 692 | F24: Exceptional Items | G24: 0 | P24: 45411 | Q24: 19096.9 | R24: 1244.1156 | S24: =(Q24-Q23)/Q23 -> 0.0053830946 | T24: =(R24-R23)/R23 -> 0.0071975755
B25: Total Current Liabilities | C25: 9588 | F25: Profit/Loss Before Tax | G25: 7186.3 | J25: Sale | K25: =G9 -> 27916.4 | L25: =_xlfn.FORMULATEXT(K25) -> =G9 | M25: = Revenue From Operations [Net] | P25: 45412 | Q25: 18970.6 | R25: 1225.7811 | S25: =(Q25-Q24)/Q24 -> -0.0066136796 | T25: =(R25-R24)/R24 -> -0.014736953
B26: Total Capital And Liabilities | C26: 38863.8 | F26: Tax Expenses-Continued Operations | J26: Variable Cost | K26: =G14+G15+G17 -> 8208.7 | L26: =_xlfn.FORMULATEXT(K26) -> =G14+G15+G17 | M26: = Cost Of Materials Consumed + Purchase Of Stock-In Trade + Changes In Inventories | P26: 45414 | Q26: 19124.449 | R26: 1242.2189 | S26: =(Q26-Q25)/Q25 -> 0.008109897 | T26: =(R26-R25)/R25 -> 0.013410016
B27: ASSETS | F27: Current Tax | G27: 1945.9 | J27: Contribution | K27: =K25-K26 -> 19707.7 | L27: =_xlfn.FORMULATEXT(K27) -> =K25-K26 | M27: = Contribution =Sales - Variable cost | P27: 45415 | Q27: 19133.4 | R27: 1254.4781 | S27: =(Q27-Q26)/Q26 -> 0.00046804861 | T27: =(R27-R26)/R26 -> 0.0098688545
B28: NON-CURRENT ASSETS | F28: Less: MAT Credit Entitlement | G28: 0 | J28: EBIT | K28: =G25+G19 -> 7357.4 | L28: =_xlfn.FORMULATEXT(K28) -> =G25+G19 | M28: = Profit/Loss Before Tax + Finance Costs | P28: 45418 | Q28: 19203.301 | R28: 1243.3944 | S28: =(Q28-Q27)/Q27 -> 0.0036533177 | T28: =(R28-R27)/R27 -> -0.0088353394
B29: Tangible Assets | C29: 6248.7 | F29: Deferred Tax | G29: -322.8 | J29: EBT | K29: =G25 -> 7186.3 | L29: =_xlfn.FORMULATEXT(K29) -> =G25 | M29: = Profit/Loss Before Tax | P29: 45419 | Q29: 18846.301 | R29: 1236.3116 | S29: =(Q29-Q28)/Q28 -> -0.018590554 | T29: =(R29-R28)/R28 -> -0.0056963129
B30: Intangible Assets | C30: 3626.8 | F30: Other Direct Taxes | G30: 0 | P30: 45420 | Q30: 18850.85 | R30: 1196.5507 | S30: =(Q30-Q29)/Q29 -> 0.00024136451 | T30: =(R30-R29)/R29 -> -0.032160974
B31: Capital Work-In-Progress | C31: 1351 | F31: Total Tax Expenses | G31: 1623.1 | J31: Beta | K31: ='DR. REDDY Beta Calc'!H7 -> 0.81295379 | P31: 45421 | Q31: 18437.051 | R31: 1161.1857 | S31: =(Q31-Q30)/Q30 -> -0.021951203 | T31: =(R31-R30)/R30 -> -0.029555782
B32: Fixed Assets | C32: 11294.8 | F32: Profit/Loss After Tax And Before ExtraOrdinary Items | G32: 5563.2 | J32: Market return (Rm) | K32: ='DR. REDDY Beta Calc'!H10*252 -> 0.11078641 | P32: 45422 | Q32: 18609.449 | R32: 1169.8096 | S32: =(Q32-Q31)/Q31 -> 0.0093506516 | T32: =(R32-R31)/R31 -> 0.0074268066
B33: Non-Current Investments | C33: 525.5 | F33: Profit/Loss From Continuing Operations | G33: 5563.2 | J33: Risk Free Rate (Rf) | K33: =6.7/100 -> 0.067 | L33: =6.7/100 | M33: = It is Standard | P33: 45425 | Q33: 18939 | R33: 1167.3497 | S33: =(Q33-Q32)/Q32 -> 0.017708787 | T33: =(R33-R32)/R32 -> -0.0021027686
B34: Deferred Tax Assets [Net] | C34: 1057.8 | F34: Profit/Loss For The Period | G34: 5563.2 | P34: 45426 | Q34: 18860.85 | R34: 1159.4966 | S34: =(Q34-Q33)/Q33 -> -0.0041264265 | T34: =(R34-R33)/R33 -> -0.0067273322
B35: Long Term Loans And Advances | C35: 0 | F35: Minority Interest | G35: 0 | P35: 45427 | Q35: 18886.551 | R35: 1160.7214 | S35: =(Q35-Q34)/Q34 -> 0.0013626731 | T35: =(R35-R34)/R34 -> 0.0010563666
B36: Other Non-Current Assets | C36: 630.3 | F36: Consolidated Profit/Loss After MI And Associates | G36: 5577.9 | P36: 45428 | Q36: 18996.15 | R36: 1155.8611 | S36: =(Q36-Q35)/Q35 -> 0.0058030506 | T36: =(R36-R35)/R35 -> -0.004187354
B37: Total Non-Current Assets | C37: 14058.5 | F37: OTHER ADDITIONAL INFORMATION | P37: 45429 | Q37: 18981.6 | R37: 1145.8148 | S37: =(Q37-Q36)/Q36 -> -0.00076598579 | T37: =(R37-R36)/R36 -> -0.0086915848
B38: CURRENT ASSETS | F38: EARNINGS PER SHARE | P38: 45433 | Q38: 19205.199 | R38: 1141.9127 | S38: =(Q38-Q37)/Q37 -> 0.011779809 | T38: =(R38-R37)/R37 -> -0.0034055238
B39: Current Investments | C39: 4405 | F39: Basic EPS (Rs.) | G39: 335 | P39: 45434 | Q39: 19317.4 | R39: 1160.277 | S39: =(Q39-Q38)/Q38 -> 0.005842229 | T39: =(R39-R38)/R38 -> 0.016082015
B40: Inventories | C40: 6355.2 | F40: Diluted EPS (Rs.) | G40: 335 | P40: 45435 | Q40: 19216.35 | R40: 1165.2063 | S40: =(Q40-Q39)/Q39 -> -0.0052310756 | T40: =(R40-R39)/R39 -> 0.0042484005
B41: Trade Receivables | C41: 8029.8 | F41: DIVIDEND AND DIVIDEND PERCENTAGE | P41: 45436 | Q41: 19119.5 | R41: 1158.8939 | S41: =(Q41-Q40)/Q40 -> -0.0050399588 | T41: =(R41-R40)/R40 -> -0.0054173908
B42: Cash And Cash Equivalents | C42: 1727.7 | F42: Equity Share Dividend | G42: 664.8 | P42: 45439 | Q42: 19111.949 | R42: 1160.267 | S42: =(Q42-Q41)/Q41 -> -0.00039492566 | T42: =(R42-R41)/R41 -> 0.0011847908
B43: Short Term Loans And Advances | C43: 0 | F43: Tax On Dividend | G43: 0 | P43: 45440 | Q43: 19215.75 | R43: 1178.562 | S43: =(Q43-Q42)/Q42 -> 0.005431198 | T43: =(R43-R42)/R42 -> 0.015767961
B44: OtherCurrentAssets | C44: 4287.6 | P44: 45441 | Q44: 19321.35 | R44: 1185.5658 | S44: =(Q44-Q43)/Q43 -> 0.0054954717 | T44: =(R44-R43)/R43 -> 0.0059426522
B45: Total Current Assets | C45: 24805.3 | P45: 45442 | Q45: 18971 | R45: 1160.4745 | S45: =(Q45-Q44)/Q44 -> -0.018132771 | T45: =(R45-R44)/R44 -> -0.021163995
B46: Total Assets | C46: 38863.8 | P46: 45443 | Q46: 18796.301 | R46: 1144.2935 | S46: =(Q46-Q45)/Q45 -> -0.0092087512 | T46: =(R46-R45)/R45 -> -0.013943461
B47: OTHER ADDITIONAL INFORMATION | P47: 45446 | Q47: 18864.15 | R47: 1142.6042 | S47: =(Q47-Q46)/Q46 -> 0.0036097321 | T47: =(R47-R46)/R46 -> -0.0014762026
B48: CONTINGENT LIABILITIES, COMMITMENTS | P48: 45447 | Q48: 18603.15 | R48: 1132.2319 | S48: =(Q48-Q47)/Q47 -> -0.013835768 | T48: =(R48-R47)/R47 -> -0.0090777839
B49: Contingent Liabilities | C49: 2091.8 | P49: 45448 | Q49: 19281.25 | R49: 1150.6749 | S49: =(Q49-Q48)/Q48 -> 0.036450794 | T49: =(R49-R48)/R48 -> 0.016289059
B50: BONUS DETAILS | P50: 45449 | Q50: 19232.1 | R50: 1163.8726 | S50: =(Q50-Q49)/Q49 -> -0.0025491288 | T50: =(R50-R49)/R49 -> 0.01146947
B51: Bonus Equity Share Capital | C51: 55.87 | P51: 45450 | Q51: 19578 | R51: 1197.5287 | S51: =(Q51-Q50)/Q50 -> 0.017985576 | T51: =(R51-R50)/R50 -> 0.028917365
B52: NON-CURRENT INVESTMENTS | P52: 45453 | Q52: 19774.699 | R52: 1206.3895 | S52: =(Q52-Q51)/Q51 -> 0.010046952 | T52: =(R52-R51)/R51 -> 0.0073992715
B53: Non-Current Investments Quoted Market Value | C53: 0 | P53: 45454 | Q53: 19689.699 | R53: 1193.1722 | S53: =(Q53-Q52)/Q52 -> -0.0042984219 | T53: =(R53-R52)/R52 -> -0.010956068
B54: Non-Current Investments Unquoted Book Value | C54: 0 | P54: 45455 | Q54: 19739.1 | R54: 1197.2816 | S54: =(Q54-Q53)/Q53 -> 0.0025089459 | T54: =(R54-R53)/R53 -> 0.0034440753
B55: CURRENT INVESTMENTS | P55: 45456 | Q55: 19838.5 | R55: 1204.3547 | S55: =(Q55-Q54)/Q54 -> 0.0050357105 | T55: =(R55-R54)/R54 -> 0.0059076495
B56: Current Investments Quoted Market Value | C56: 0 | P56: 45457 | Q56: 19895.65 | R56: 1202.2605 | S56: =(Q56-Q55)/Q55 -> 0.0028807818 | T56: =(R56-R55)/R55 -> -0.0017388882
B57: Current Investments Unquoted Book Value | C57: 0 | P57: 45461 | Q57: 19826.65 | R57: 1183.689 | S57: =(Q57-Q56)/Q56 -> -0.0034680947 | T57: =(R57-R56)/R56 -> -0.015447179
P58: 45462 | Q58: 19644.5 | R58: 1176.764 | S58: =(Q58-Q57)/Q57 -> -0.009187149 | T58: =(R58-R57)/R57 -> -0.0058502926
P59: 45463 | Q59: 19544.551 | R59: 1179.6487 | S59: =(Q59-Q58)/Q58 -> -0.0050878983 | T59: =(R59-R58)/R58 -> 0.0024513356
P60: 45464 | Q60: 19528.4 | R60: 1187.6798 | S60: =(Q60-Q59)/Q59 -> -0.00082633726 | T60: =(R60-R59)/R59 -> 0.0068080676
P61: 45467 | Q61: 19521.15 | R61: 1196.274 | S61: =(Q61-Q60)/Q60 -> -0.00037125417 | T61: =(R61-R60)/R60 -> 0.0072361576
P62: 45468 | Q62: 19532.301 | R62: 1200.9071 | S62: =(Q62-Q61)/Q61 -> 0.00057119537 | T62: =(R62-R61)/R61 -> 0.0038729058
P63: 45469 | Q63: 19545.35 | R63: 1199.2574 | S63: =(Q63-Q62)/Q62 -> 0.00066806406 | T63: =(R63-R62)/R62 -> -0.0013736768
P64: 45470 | Q64: 19514.801 | R64: 1232.0243 | S64: =(Q64-Q63)/Q63 -> -0.0015629717 | T64: =(R64-R63)/R63 -> 0.027322612
P65: 45471 | Q65: 19731.551 | R65: 1264.9098 | S65: =(Q65-Q64)/Q64 -> 0.011106954 | T65: =(R65-R64)/R64 -> 0.026692248
P66: 45474 | Q66: 19758.25 | R66: 1255.298 | S66: =(Q66-Q65)/Q65 -> 0.0013531232 | T66: =(R66-R65)/R65 -> -0.0075988157
P67: 45475 | Q67: 19786.4 | R67: 1258.5677 | S67: =(Q67-Q66)/Q66 -> 0.0014247411 | T67: =(R67-R66)/R66 -> 0.0026047803
P68: 45476 | Q68: 19915.301 | R68: 1269.5625 | S68: =(Q68-Q67)/Q67 -> 0.0065145953 | T68: =(R68-R67)/R67 -> 0.008735923
P69: 45477 | Q69: 20192.6 | R69: 1280.1226 | S69: =(Q69-Q68)/Q68 -> 0.013923909 | T69: =(R69-R68)/R68 -> 0.0083178722
... P252: 45744 | Q252: 21137.449 | R252: 1136.989 | S252: =(Q252-Q251)/Q251 -> -0.0064723948 | T252: =(R252-R251)/R251 -> -0.015487899

Sheet LUPIN Beta Calc
C2: LUPIN.NS
A3: Price | B3: Close | C3: Close | D3: Return | E3: Return | H3: Covarience(Market/company) | I3: Varience (Market)
A4: Ticker | B4: ^CNXPHARMA | C4: LUPIN.NS | D4: Nifty | E4: Company | H4: =_xlfn.COVARIANCE.S(D7:D252,E7:E252) -> 0.00013062993 | I4: =_xlfn.VAR.S(D7:D252) -> 0.00010123143
A5: Date
A6: 45383 | B6: 19207.9 | C6: 1606.6694 | H6: Beta
A7: 45384 | B7: 19185.15 | C7: 1592.9652 | D7: =(B7-B6)/B6 -> -0.0011844085 | E7: =(C7-C6)/C6 -> -0.0085295851 | H7: =H4/I4 -> 1.2904088
A8: 45385 | B8: 19153.051 | C8: 1588.5126 | D8: =(B8-B7)/B7 -> -0.0016731487 | E8: =(C8-C7)/C7 -> -0.0027951877
A9: 45386 | B9: 19125.199 | C9: 1570.5535 | D9: =(B9-B8)/B8 -> -0.001454158 | E9: =(C9-C8)/C8 -> -0.011305612 | H9: Market Return
A10: 45387 | B10: 19160.75 | C10: 1582.4272 | D10: =(B10-B9)/B9 -> 0.001858845 | E10: =(C10-C9)/C9 -> 0.0075602516 | H10: =AVERAGE(D7:D252) -> 0.00043962859
A11: 45390 | B11: 19218.85 | C11: 1595.0431 | D11: =(B11-B10)/B10 -> 0.00303222 | E11: =(C11-C10)/C10 -> 0.0079724643
A12: 45391 | B12: 19182.301 | C12: 1588.76 | D12: =(B12-B11)/B11 -> -0.0019017178 | E12: =(C12-C11)/C11 -> -0.0039391294
A13: 45392 | B13: 19117 | C13: 1587.7209 | D13: =(B13-B12)/B12 -> -0.0034042205 | E13: =(C13-C12)/C12 -> -0.00065400847
A14: 45394 | B14: 18788.65 | C14: 1605.1853 | D14: =(B14-B13)/B13 -> -0.017175792 | E14: =(C14-C13)/C13 -> 0.010999638
A15: 45397 | B15: 18617.65 | C15: 1592.1736 | D15: =(B15-B14)/B14 -> -0.0091012391 | E15: =(C15-C14)/C14 -> -0.008106054
A16: 45398 | B16: 18695.6 | C16: 1594.4988 | D16: =(B16-B15)/B15 -> 0.0041868451 | E16: =(C16-C15)/C15 -> 0.0014603906
A17: 45400 | B17: 18525.75 | C17: 1577.2819 | D17: =(B17-B16)/B16 -> -0.0090850046 | E17: =(C17-C16)/C16 -> -0.0107977
A18: 45401 | B18: 18404.6 | C18: 1531.2711 | D18: =(B18-B17)/B17 -> -0.0065395674 | E18: =(C18-C17)/C17 -> -0.029170907
A19: 45404 | B19: 18643 | C19: 1586.7809 | D19: =(B19-B18)/B18 -> 0.012953305 | E19: =(C19-C18)/C18 -> 0.036250776
A20: 45405 | B20: 18463.75 | C20: 1563.4292 | D20: =(B20-B19)/B19 -> -0.0096148689 | E20: =(C20-C19)/C19 -> -0.014716389
A21: 45406 | B21: 18586.199 | C21: 1563.3798 | D21: =(B21-B20)/B20 -> 0.0066318716 | E21: =(C21-C20)/C20 -> -3.162182e-05
A22: 45407 | B22: 18878.15 | C22: 1577.6283 | D22: =(B22-B21)/B21 -> 0.015707955 | E22: =(C22-C21)/C21 -> 0.0091139309
... A252: 45744 | B252: 21137.449 | C252: 2015.4149 | D252: =(B252-B251)/B251 -> -0.0064723948 | E252: =(C252-C251)/C251 -> 0.004532305

Sheet LUPIN
C2: LUPIN | P2: LUPIN.NS
P3: Price | Q3: Close | R3: Close | S3: Return | T3: Return | W3: Covarience(Market/company) | X3: Varience (Market)
B4: Balance Sheet of Lupin (in Rs. Cr.) | C4: 46105 | F4: Profit & Loss account of Lupin (in Rs. Cr.) | G4: 46105 | P4: Ticker | Q4: ^CNXPHARMA | R4: LUPIN.NS | S4: Nifty | T4: Company | W4: =_xlfn.COVARIANCE.S(S7:S252,T7:T252) -> 0.00013062993 | X4: =_xlfn.VAR.S(S7:S252) -> 0.00010123143
C5: 12 mths | G5: 12 mths | P5: Date
B6: EQUITIES AND LIABILITIES | F6: INCOME | P6: 45383 | Q6: 19207.9 | R6: 1606.6694 | W6: Beta
B7: SHAREHOLDER'S FUNDS | F7: Revenue From Operations [Gross] | G7: 19656.34 | P7: 45384 | Q7: 19185.15 | R7: 1592.9652 | S7: =(Q7-Q6)/Q6 -> -0.0011844085 | T7: =(R7-R6)/R6 -> -0.0085295851 | W7: =W4/X4 -> 1.2904088
B8: Equity Share Capital | C8: 91.14 | F8: Less: Excise/Sevice Tax/Other Levies | G8: 0 | P8: 45385 | Q8: 19153.051 | R8: 1588.5126 | S8: =(Q8-Q7)/Q7 -> -0.0016731487 | T8: =(R8-R7)/R7 -> -0.0027951877
B9: Total Share Capital | C9: 91.14 | F9: Revenue From Operations [Net] | G9: 19656.34 | P9: 45386 | Q9: 19125.199 | R9: 1570.5535 | S9: =(Q9-Q8)/Q8 -> -0.001454158 | T9: =(R9-R8)/R8 -> -0.011305612 | W9: Market Return
B10: Reserves and Surplus | C10: 14084.7 | F10: Total Operating Revenues | G10: 20010.82 | P10: 45387 | Q10: 19160.75 | R10: 1582.4272 | S10: =(Q10-Q9)/Q9 -> 0.001858845 | T10: =(R10-R9)/R9 -> 0.0075602516 | W10: =AVERAGE(S7:S252) -> 0.00043962859
B11: Total Reserves and Surplus | C11: 14084.7 | F11: Other Income | G11: 120.17 | P11: 45390 | Q11: 19218.85 | R11: 1595.0431 | S11: =(Q11-Q10)/Q10 -> 0.00303222 | T11: =(R11-R10)/R10 -> 0.0079724643
B12: Total Shareholders Funds | C12: 14290.21 | F12: Total Revenue | G12: 20130.99 | P12: 45391 | Q12: 19182.301 | R12: 1588.76 | S12: =(Q12-Q11)/Q11 -> -0.0019017178 | T12: =(R12-R11)/R11 -> -0.0039391294
B13: Minority Interest | C13: 83.16 | F13: EXPENSES | J13: Total Debt | K13: =C15 + C21 -> 2669.91 | L13: =_xlfn.FORMULATEXT(K13) -> =C15 + C21 | M13: = Longterm borrowings + shortterm borrowings | P13: 45392 | Q13: 19117 | R13: 1587.7209 | S13: =(Q13-Q12)/Q12 -> -0.0034042205 | T13: =(R13-R12)/R12 -> -0.00065400847
B14: NON-CURRENT LIABILITIES | F14: Cost Of Materials Consumed | G14: 4142.19 | J14: DOL | K14: =K27 / K28 -> 4.7598541 | L14: =_xlfn.FORMULATEXT(K14) -> =K27 / K28 | M14: =Contribution/EBIT | P14: 45394 | Q14: 18788.65 | R14: 1605.1853 | S14: =(Q14-Q13)/Q13 -> -0.017175792 | T14: =(R14-R13)/R13 -> 0.010999638
B15: Long Term Borrowings | C15: 0 | F15: Purchase Of Stock-In Trade | G15: 2958.72 | J15: DFL | K15: =K28 / K29 -> 1.1286438 | L15: =_xlfn.FORMULATEXT(K15) -> =K28 / K29 | M15: =EBIT/EBT | P15: 45397 | Q15: 18617.65 | R15: 1592.1736 | S15: =(Q15-Q14)/Q14 -> -0.0091012391 | T15: =(R15-R14)/R14 -> -0.008106054
B16: Deferred Tax Liabilities [Net] | C16: 245.87 | F16: Operating And Direct Expenses | G16: 0 | J16: DTL | K16: =K14 * K15 -> 5.3721798 | L16: =_xlfn.FORMULATEXT(K16) -> =K14 * K15 | M16: =DOL * DFL | P16: 45398 | Q16: 18695.6 | R16: 1594.4988 | S16: =(Q16-Q15)/Q15 -> 0.0041868451 | T16: =(R16-R15)/R15 -> 0.0014603906
B17: Other Long Term Liabilities | C17: 500.96 | F17: Changes In Inventories Of FGWIP And Stock In Trade | G17: -457.44 | J17: Cost of Debt (Rd) | K17: =G19 / (C15 + C21) -> 0.1167118 | L17: =_xlfn.FORMULATEXT(K17) -> =G19 / (C15 + C21) | M17: =Interest/Total Debt | P17: 45400 | Q17: 18525.75 | R17: 1577.2819 | S17: =(Q17-Q16)/Q16 -> -0.0090850046 | T17: =(R17-R16)/R16 -> -0.0107977
B18: Long Term Provisions | C18: 375.4 | F18: Employee Benefit Expenses | G18: 3494.57 | J18: Cost of Equity (Re) | K18: =K33+K31*(K32-K33) -> 0.12350236 | L18: =_xlfn.FORMULATEXT(K18) -> =K33+K31*(K32-K33) | M18: = RF + Beta(Rm-Rf) | P18: 45401 | Q18: 18404.6 | R18: 1531.2711 | S18: =(Q18-Q17)/Q17 -> -0.0065395674 | T18: =(R18-R17)/R17 -> -0.029170907
B19: Total Non-Current Liabilities | C19: 1122.23 | F19: Finance Costs | G19: 311.61 | J19: Tax Rate | K19: =G31 / G25 -> 0.20092723 | L19: =_xlfn.FORMULATEXT(K19) -> =G31 / G25 | M19: =Tax/EBT | P19: 45404 | Q19: 18643 | R19: 1586.7809 | S19: =(Q19-Q18)/Q18 -> 0.012953305 | T19: =(R19-R18)/R18 -> 0.036250776
B20: CURRENT LIABILITIES | F20: Depreciation And Amortisation Expenses | G20: 1196.81 | J20: Weight of Debt | K20: =K13 / (K13 + C12) -> 0.15742282 | L20: =_xlfn.FORMULATEXT(K20) -> =K13 / (K13 + C12) | M20: =Debt/(Debt+Equity) | P20: 45405 | Q20: 18463.75 | R20: 1563.4292 | S20: =(Q20-Q19)/Q19 -> -0.0096148689 | T20: =(R20-R19)/R19 -> -0.014716389
B21: Short Term Borrowings | C21: 2669.91 | F21: Other Expenses | G21: 6062.26 | J21: Weight of Equity | K21: =C12 / (K13 + C12) -> 0.84257718 | L21: =_xlfn.FORMULATEXT(K21) -> =C12 / (K13 + C12) | M21: =Equity/(Debt+Equity) | P21: 45406 | Q21: 18586.199 | R21: 1563.3798 | S21: =(Q21-Q20)/Q20 -> 0.0066318716 | T21: =(R21-R20)/R20 -> -3.162182e-05
B22: Trade Payables | C22: 2958.11 | F22: Total Expenses | G22: 17708.72 | J22: WACC | K22: =K21 * K18 + K20 * K17 -> 0.12243337 | L22: =_xlfn.FORMULATEXT(K22) -> =K21 * K18 + K20 * K17 | M22: =(Equity Weight×Cost of Equity)+(Debt Weight×Cost of Debt) | P22: 45407 | Q22: 18878.15 | R22: 1577.6283 | S22: =(Q22-Q21)/Q21 -> 0.015707955 | T22: =(R22-R21)/R21 -> 0.0091139309
B23: Other Current Liabilities | C23: 2348.54 | F23: Profit/Loss Before Exceptional, ExtraOrdinary Items And Tax | G23: 2422.27 | P23: 45408 | Q23: 18994.65 | R23: 1598.9514 | S23: =(Q23-Q22)/Q22 -> 0.0061711554 | T23: =(R23-R22)/R22 -> 0.013515934
B24: Short Term Provisions | C24: 524.94 | F24: Exceptional Items | G24: 0 | P24: 45411 | Q24: 19096.9 | R24: 1620.2253 | S24: =(Q24-Q23)/Q23 -> 0.0053830946 | T24: =(R24-R23)/R23 -> 0.013304923
B25: Total Current Liabilities | C25: 8501.5 | F25: Profit/Loss Before Tax | G25: 2422.27 | J25: Sale | K25: =G9 -> 19656.34 | L25: =_xlfn.FORMULATEXT(K25) -> =G9 | M25: = Revenue From Operations [Net] | P25: 45412 | Q25: 18970.6 | R25: 1628.5864 | S25: =(Q25-Q24)/Q24 -> -0.0066136796 | T25: =(R25-R24)/R24 -> 0.0051604451
B26: Total Capital And Liabilities | C26: 23997.18 | F26: Tax Expenses-Continued Operations | J26: Variable Cost | K26: =G14+G15+G17 -> 6643.47 | L26: =_xlfn.FORMULATEXT(K26) -> =G14+G15+G17 | M26: = Cost Of Materials Consumed + Purchase Of Stock-In Trade + Changes In Inventories | P26: 45414 | Q26: 19124.449 | R26: 1630.3181 | S26: =(Q26-Q25)/Q25 -> 0.008109897 | T26: =(R26-R25)/R25 -> 0.0010633083
B27: ASSETS | F27: Current Tax | G27: 633.85 | J27: Contribution | K27: =K25-K26 -> 13012.87 | L27: =_xlfn.FORMULATEXT(K27) -> =K25-K26 | M27: = Contribution =Sales - Variable cost | P27: 45415 | Q27: 19133.4 | R27: 1637.3434 | S27: =(Q27-Q26)/Q26 -> 0.00046804861 | T27: =(R27-R26)/R26 -> 0.0043091397
B28: NON-CURRENT ASSETS | F28: Less: MAT Credit Entitlement | G28: 0 | J28: EBIT | K28: =G25+G19 -> 2733.88 | L28: =_xlfn.FORMULATEXT(K28) -> =G25+G19 | M28: = Profit/Loss Before Tax + Finance Costs | P28: 45418 | Q28: 19203.301 | R28: 1661.9816 | S28: =(Q28-Q27)/Q27 -> 0.0036533177 | T28: =(R28-R27)/R27 -> 0.015047658
B29: Tangible Assets | C29: 4898.55 | F29: Deferred Tax | G29: -147.15 | J29: EBT | K29: =G25 -> 2422.27 | L29: =_xlfn.FORMULATEXT(K29) -> =G25 | M29: = Profit/Loss Before Tax | P29: 45419 | Q29: 18846.301 | R29: 1593.6578 | S29: =(Q29-Q28)/Q28 -> -0.018590554 | T29: =(R29-R28)/R28 -> -0.0411098
B30: Intangible Assets | C30: 1654.71 | F30: Other Direct Taxes | G30: 0 | P30: 45420 | Q30: 18850.85 | R30: 1599.1494 | S30: =(Q30-Q29)/Q29 -> 0.00024136451 | T30: =(R30-R29)/R29 -> 0.0034458947
B31: Capital Work-In-Progress | C31: 595.67 | F31: Total Tax Expenses | G31: 486.7 | J31: Beta | K31: ='LUPIN Beta Calc'!H7 -> 1.2904088 | P31: 45421 | Q31: 18437.051 | R31: 1567.2882 | S31: =(Q31-Q30)/Q30 -> -0.021951203 | T31: =(R31-R30)/R30 -> -0.019923846
B32: Fixed Assets | C32: 7325.79 | F32: Profit/Loss After Tax And Before ExtraOrdinary Items | G32: 1935.57 | J32: Market return (Rm) | K32: ='LUPIN Beta Calc'!H10*252 -> 0.11078641 | P32: 45422 | Q32: 18609.449 | R32: 1591.6294 | S32: =(Q32-Q31)/Q31 -> 0.0093506516 | T32: =(R32-R31)/R31 -> 0.015530766
B33: Non-Current Investments | C33: 227.7 | F33: Profit/Loss From Continuing Operations | G33: 1935.57 | J33: Risk Free Rate (Rf) | K33: =6.7/100 -> 0.067 | L33: =6.7/100 | M33: = It is Standard | P33: 45425 | Q33: 18939 | R33: 1670.8374 | S33: =(Q33-Q32)/Q32 -> 0.017708787 | T33: =(R33-R32)/R32 -> 0.049765359
B34: Deferred Tax Assets [Net] | C34: 302.53 | F34: Profit/Loss For The Period | G34: 1935.57 | P34: 45426 | Q34: 18860.85 | R34: 1619.9286 | S34: =(Q34-Q33)/Q33 -> -0.0041264265 | T34: =(R34-R33)/R33 -> -0.030469041
B35: Long Term Loans And Advances | C35: 3.57 | F35: Minority Interest | G35: -21.09 | P35: 45427 | Q35: 18886.551 | R35: 1621.858 | S35: =(Q35-Q34)/Q34 -> 0.0013626731 | T35: =(R35-R34)/R34 -> 0.0011910669
B36: Other Non-Current Assets | C36: 364.9 | F36: Consolidated Profit/Loss After MI And Associates | G36: 1914.48 | P36: 45428 | Q36: 18996.15 | R36: 1645.4572 | S36: =(Q36-Q35)/Q35 -> 0.0058030506 | T36: =(R36-R35)/R35 -> 0.01455067
B37: Total Non-Current Assets | C37: 10549.53 | F37: OTHER ADDITIONAL INFORMATION | P37: 45429 | Q37: 18981.6 | R37: 1634.3749 | S37: =(Q37-Q36)/Q36 -> -0.00076598579 | T37: =(R37-R36)/R36 -> -0.0067350738
B38: CURRENT ASSETS | F38: EARNINGS PER SHARE | P38: 45433 | Q38: 19205.199 | R38: 1666.1372 | S38: =(Q38-Q37)/Q37 -> 0.011779809 | T38: =(R38-R37)/R37 -> 0.019433931
B39: Current Investments | C39: 846.93 | F39: Basic EPS (Rs.) | G39: 42 | P39: 45434 | Q39: 19317.4 | R39: 1697.7512 | S39: =(Q39-Q38)/Q38 -> 0.005842229 | T39: =(R39-R38)/R38 -> 0.018974436
B40: Inventories | C40: 4953.9 | F40: Diluted EPS (Rs.) | G40: 42 | P40: 45435 | Q40: 19216.35 | R40: 1615.4758 | S40: =(Q40-Q39)/Q39 -> -0.0052310756 | T40: =(R40-R39)/R39 -> -0.048461394
B41: Trade Receivables | C41: 4692.05 | F41: DIVIDEND AND DIVIDEND PERCENTAGE | P41: 45436 | Q41: 19119.5 | R41: 1597.3684 | S41: =(Q41-Q40)/Q40 -> -0.0050399588 | T41: =(R41-R40)/R40 -> -0.011208723
B42: Cash And Cash Equivalents | C42: 1202.54 | F42: Equity Share Dividend | G42: 182.03 | P42: 45439 | Q42: 19111.949 | R42: 1599.1 | S42: =(Q42-Q41)/Q41 -> -0.00039492566 | T42: =(R42-R41)/R41 -> 0.0010840125
B43: Short Term Loans And Advances | C43: 2.58 | F43: Tax On Dividend | G43: 0 | P43: 45440 | Q43: 19215.75 | R43: 1586.583 | S43: =(Q43-Q42)/Q42 -> 0.005431198 | T43: =(R43-R42)/R42 -> -0.007827508
B44: OtherCurrentAssets | C44: 1749.65 | P44: 45441 | Q44: 19321.35 | R44: 1584.604 | S44: =(Q44-Q43)/Q43 -> 0.0054954717 | T44: =(R44-R43)/R43 -> -0.0012473371
B45: Total Current Assets | C45: 13447.65 | P45: 45442 | Q45: 18971 | R45: 1562.786 | S45: =(Q45-Q44)/Q44 -> -0.018132771 | T45: =(R45-R44)/R44 -> -0.013768735
B46: Total Assets | C46: 23997.18 | P46: 45443 | Q46: 18796.301 | R46: 1565.903 | S46: =(Q46-Q45)/Q45 -> -0.0092087512 | T46: =(R46-R45)/R45 -> 0.0019944787
B47: OTHER ADDITIONAL INFORMATION | P47: 45446 | Q47: 18864.15 | R47: 1567.2882 | S47: =(Q47-Q46)/Q46 -> 0.0036097321 | T47: =(R47-R46)/R46 -> 0.00088463586
B48: CONTINGENT LIABILITIES, COMMITMENTS | P48: 45447 | Q48: 18603.15 | R48: 1548.2902 | S48: =(Q48-Q47)/Q47 -> -0.013835768 | T48: =(R48-R47)/R47 -> -0.012121604
B49: Contingent Liabilities | C49: 1148.59 | P49: 45448 | Q49: 19281.25 | R49: 1613.3485 | S49: =(Q49-Q48)/Q48 -> 0.036450794 | T49: =(R49-R48)/R48 -> 0.042019481
B50: BONUS DETAILS | P50: 45449 | Q50: 19232.1 | R50: 1590.343 | S50: =(Q50-Q49)/Q49 -> -0.0025491288 | T50: =(R50-R49)/R49 -> -0.014259469
B51: Bonus Equity Share Capital | C51: 40.15 | P51: 45450 | Q51: 19578 | R51: 1612.4086 | S51: =(Q51-Q50)/Q50 -> 0.017985576 | T51: =(R51-R50)/R50 -> 0.013874712
B52: NON-CURRENT INVESTMENTS | P52: 45453 | Q52: 19774.699 | R52: 1616.9602 | S52: =(Q52-Q51)/Q51 -> 0.010046952 | T52: =(R52-R51)/R51 -> 0.0028228799
B53: Non-Current Investments Quoted Market Value | C53: 0 | P53: 45454 | Q53: 19689.699 | R53: 1597.0715 | S53: =(Q53-Q52)/Q52 -> -0.0042984219 | T53: =(R53-R52)/R52 -> -0.012300038
B54: Non-Current Investments Unquoted Book Value | C54: 200.79 | P54: 45455 | Q54: 19739.1 | R54: 1588.661 | S54: =(Q54-Q53)/Q53 -> 0.0025089459 | T54: =(R54-R53)/R53 -> -0.0052662152
B55: CURRENT INVESTMENTS | P55: 45456 | Q55: 19838.5 | R55: 1588.562 | S55: =(Q55-Q54)/Q54 -> 0.0050357105 | T55: =(R55-R54)/R54 -> -6.2316015e-05
B56: Current Investments Quoted Market Value | C56: 0 | P56: 45457 | Q56: 19895.65 | R56: 1587.2262 | S56: =(Q56-Q55)/Q55 -> 0.0028807818 | T56: =(R56-R55)/R55 -> -0.00084089599
B57: Current Investments Unquoted Book Value | C57: 846.93 | P57: 45461 | Q57: 19826.65 | R57: 1564.8145 | S57: =(Q57-Q56)/Q56 -> -0.0034680947 | T57: =(R57-R56)/R56 -> -0.014120069
P58: 45462 | Q58: 19644.5 | R58: 1555.7607 | S58: =(Q58-Q57)/Q57 -> -0.009187149 | T58: =(R58-R57)/R57 -> -0.0057858048
P59: 45463 | Q59: 19544.551 | R59: 1539.3353 | S59: =(Q59-Q58)/Q58 -> -0.0050878983 | T59: =(R59-R58)/R58 -> -0.010557803
P60: 45464 | Q60: 19528.4 | R60: 1544.5796 | S60: =(Q60-Q59)/Q59 -> -0.00082633726 | T60: =(R60-R59)/R59 -> 0.0034068358
P61: 45467 | Q61: 19521.15 | R61: 1550.2692 | S61: =(Q61-Q60)/Q60 -> -0.00037125417 | T61: =(R61-R60)/R60 -> 0.0036835753
P62: 45468 | Q62: 19532.301 | R62: 1542.4521 | S62: =(Q62-Q61)/Q61 -> 0.00057119537 | T62: =(R62-R61)/R61 -> -0.0050423609
P63: 45469 | Q63: 19545.35 | R63: 1566.9913 | S63: =(Q63-Q62)/Q62 -> 0.00066806406 | T63: =(R63-R62)/R62 -> 0.015909203
P64: 45470 | Q64: 19514.801 | R64: 1566.7439 | S64: =(Q64-Q63)/Q63 -> -0.0015629717 | T64: =(R64-R63)/R63 -> -0.00015790548
P65: 45471 | Q65: 19731.551 | R65: 1604.2947 | S65: =(Q65-Q64)/Q64 -> 0.011106954 | T65: =(R65-R64)/R64 -> 0.023967402
P66: 45474 | Q66: 19758.25 | R66: 1599.0505 | S66: =(Q66-Q65)/Q65 -> 0.0013531232 | T66: =(R66-R65)/R65 -> -0.0032688138
P67: 45475 | Q67: 19786.4 | R67: 1615.6244 | S67: =(Q67-Q66)/Q66 -> 0.0014247411 | T67: =(R67-R66)/R66 -> 0.010364808
P68: 45476 | Q68: 19915.301 | R68: 1613.4475 | S68: =(Q68-Q67)/Q67 -> 0.0065145953 | T68: =(R68-R67)/R67 -> -0.0013473923
P69: 45477 | Q69: 20192.6 | R69: 1740.7936 | S69: =(Q69-Q68)/Q68 -> 0.013923909 | T69: =(R69-R68)/R68 -> 0.078927928
... P252: 45744 | Q252: 21137.449 | R252: 2015.4149 | S252: =(Q252-Q251)/Q251 -> -0.0064723948 | T252: =(R252-R251)/R251 -> 0.004532305

Sheet DIVISLAB Beta Calc
C2: DIVISLAB.NS
A3: Price | B3: Close | C3: Close | D3: Return | E3: Return | H3: Covarience(Market/company) | I3: Varience (Market)
A4: Ticker | B4: ^CNXPHARMA | C4: DIVISLAB.NS | D4: Nifty | E4: Company | H4: =_xlfn.COVARIANCE.S(D7:D252,E7:E252) -> 0.00010872479 | I4: =_xlfn.VAR.S(D7:D252) -> 0.00010123143
A5: Date
A6: 45383 | B6: 19207.9 | C6: 3530.1108 | H6: Beta
A7: 45384 | B7: 19185.15 | C7: 3584.0823 | D7: =(B7-B6)/B6 -> -0.0011844085 | E7: =(C7-C6)/C6 -> 0.015288878 | H7: =H4/I4 -> 1.0740221
A8: 45385 | B8: 19153.051 | C8: 3645.8206 | D8: =(B8-B7)/B7 -> -0.0016731487 | E8: =(C8-C7)/C7 -> 0.017225687
A9: 45386 | B9: 19125.199 | C9: 3694.5977 | D9: =(B9-B8)/B8 -> -0.001454158 | E9: =(C9-C8)/C8 -> 0.013378908 | H9: Market Return
A10: 45387 | B10: 19160.75 | C10: 3708.3997 | D10: =(B10-B9)/B9 -> 0.001858845 | E10: =(C10-C9)/C9 -> 0.0037357253 | H10: =AVERAGE(D7:D252) -> 0.00043962859
A11: 45390 | B11: 19218.85 | C11: 3755.7424 | D11: =(B11-B10)/B10 -> 0.00303222 | E11: =(C11-C10)/C10 -> 0.012766362
A12: 45391 | B12: 19182.301 | C12: 3764.5974 | D12: =(B12-B11)/B11 -> -0.0019017178 | E12: =(C12-C11)/C11 -> 0.0023577177
A13: 45392 | B13: 19117 | C13: 3699.446 | D13: =(B13-B12)/B12 -> -0.0034042205 | E13: =(C13-C12)/C12 -> -0.017306331
A14: 45394 | B14: 18788.65 | C14: 3739.6152 | D14: =(B14-B13)/B13 -> -0.017175792 | E14: =(C14-C13)/C13 -> 0.010858163
A15: 45397 | B15: 18617.65 | C15: 3677.135 | D15: =(B15-B14)/B14 -> -0.0091012391 | E15: =(C15-C14)/C14 -> -0.016707661
A16: 45398 | B16: 18695.6 | C16: 3724.2795 | D16: =(B16-B15)/B15 -> 0.0041868451 | E16: =(C16-C15)/C15 -> 0.012820995
A17: 45400 | B17: 18525.75 | C17: 3669.5659 | D17: =(B17-B16)/B16 -> -0.0090850046 | E17: =(C17-C16)/C16 -> -0.014691062
A18: 45401 | B18: 18404.6 | C18: 3632.7605 | D18: =(B18-B17)/B17 -> -0.0065395674 | E18: =(C18-C17)/C17 -> -0.010029911
A19: 45404 | B19: 18643 | C19: 3697.8628 | D19: =(B19-B18)/B18 -> 0.012953305 | E19: =(C19-C18)/C18 -> 0.017920888
A20: 45405 | B20: 18463.75 | C20: 3728.6821 | D20: =(B20-B19)/B19 -> -0.0096148689 | E20: =(C20-C19)/C19 -> 0.0083343644
A21: 45406 | B21: 18586.199 | C21: 3773.3535 | D21: =(B21-B20)/B20 -> 0.0066318716 | E21: =(C21-C20)/C20 -> 0.011980476
A22: 45407 | B22: 18878.15 | C22: 3803.0356 | D22: =(B22-B21)/B21 -> 0.015707955 | E22: =(C22-C21)/C21 -> 0.0078662465
... A252: 45744 | B252: 21137.449 | C252: 5749.2715 | D252: =(B252-B251)/B251 -> -0.0064723948 | E252: =(C252-C251)/C251 -> -0.016551277

Sheet Divis Labs
C2: DIVIS Laboratories Ltd. | P2: DIVISLAB.NS
P3: Price | Q3: Close | R3: Close | S3: Return | T3: Return | W3: Covarience(Market/company) | X3: Varience (Market)
B4: Balance Sheet of Divis Laboratories (in Rs. Cr.) | C4: 46105 | F4: Profit & Loss account of Divis Laboratories (in Rs. Cr.) | G4: 46105 | P4: Ticker | Q4: ^CNXPHARMA | R4: DIVISLAB.NS | S4: Nifty | T4: Company | W4: =_xlfn.COVARIANCE.S(S7:S252,T7:T252) -> 0.00010872479 | X4: =_xlfn.VAR.S(S7:S252) -> 0.00010123143
C5: 12 mths | G5: 12 mths | P5: Date
B6: EQUITIES AND LIABILITIES | F6: INCOME | P6: 45383 | Q6: 19207.9 | R6: 3530.1108 | W6: Beta
B7: SHAREHOLDER'S FUNDS | F7: Revenue From Operations [Gross] | G7: 7796 | P7: 45384 | Q7: 19185.15 | R7: 3584.0823 | S7: =(Q7-Q6)/Q6 -> -0.0011844085 | T7: =(R7-R6)/R6 -> 0.015288878 | W7: =W4/X4 -> 1.0740221
B8: Equity Share Capital | C8: 53 | F8: Less: Excise/Sevice Tax/Other Levies | G8: 0 | P8: 45385 | Q8: 19153.051 | R8: 3645.8206 | S8: =(Q8-Q7)/Q7 -> -0.0016731487 | T8: =(R8-R7)/R7 -> 0.017225687
B9: Total Share Capital | C9: 53 | F9: Revenue From Operations [Net] | G9: 7796 | P9: 45386 | Q9: 19125.199 | R9: 3694.5977 | S9: =(Q9-Q8)/Q8 -> -0.001454158 | T9: =(R9-R8)/R8 -> 0.013378908 | W9: Market Return
B10: Reserves and Surplus | C10: 13518 | F10: Total Operating Revenues | G10: 7845 | P10: 45387 | Q10: 19160.75 | R10: 3708.3997 | S10: =(Q10-Q9)/Q9 -> 0.001858845 | T10: =(R10-R9)/R9 -> 0.0037357253 | W10: =AVERAGE(S7:S252) -> 0.00043962859
B11: Total Reserves and Surplus | C11: 13518 | F11: Other Income | G11: 339 | P11: 45390 | Q11: 19218.85 | R11: 3755.7424 | S11: =(Q11-Q10)/Q10 -> 0.00303222 | T11: =(R11-R10)/R10 -> 0.012766362
B12: Total Shareholders Funds | C12: 13571 | F12: Total Revenue | G12: 8184 | P12: 45391 | Q12: 19182.301 | R12: 3764.5974 | S12: =(Q12-Q11)/Q11 -> -0.0019017178 | T12: =(R12-R11)/R11 -> 0.0023577177
B13: Minority Interest | C13: 0 | F13: EXPENSES | J13: Total Debt | K13: =C15 + C21 -> 0 | L13: =_xlfn.FORMULATEXT(K13) -> =C15 + C21 | M13: = Longterm borrowings + shortterm borrowings | P13: 45392 | Q13: 19117 | R13: 3699.446 | S13: =(Q13-Q12)/Q12 -> -0.0034042205 | T13: =(R13-R12)/R12 -> -0.017306331
B14: NON-CURRENT LIABILITIES | F14: Cost Of Materials Consumed | G14: 3232 | J14: DOL | K14: =K27 / K28 -> 2.154663 | L14: =_xlfn.FORMULATEXT(K14) -> =K27 / K28 | M14: =Contribution/EBIT | P14: 45394 | Q14: 18788.65 | R14: 3739.6152 | S14: =(Q14-Q13)/Q13 -> -0.017175792 | T14: =(R14-R13)/R13 -> 0.010858163
B15: Long Term Borrowings | C15: 0 | F15: Purchase Of Stock-In Trade | G15: 6 | J15: DFL | K15: =K28 / K29 -> 1.001387 | L15: =_xlfn.FORMULATEXT(K15) -> =K28 / K29 | M15: =EBIT/EBT | P15: 45397 | Q15: 18617.65 | R15: 3677.135 | S15: =(Q15-Q14)/Q14 -> -0.0091012391 | T15: =(R15-R14)/R14 -> -0.016707661
B16: Deferred Tax Liabilities [Net] | C16: 582 | F16: Operating And Direct Expenses | G16: 0 | J16: DTL | K16: =K14 * K15 -> 2.1576514 | L16: =_xlfn.FORMULATEXT(K16) -> =K14 * K15 | M16: =DOL * DFL | P16: 45398 | Q16: 18695.6 | R16: 3724.2795 | S16: =(Q16-Q15)/Q15 -> 0.0041868451 | T16: =(R16-R15)/R15 -> 0.012820995
B17: Other Long Term Liabilities | C17: 2 | F17: Changes In Inventories Of FGWIP And Stock In Trade | G17: -109 | J17: Cost of Debt (Rd) | K17: 0 | L17: - | M17: =Interest/Total Debt | P17: 45400 | Q17: 18525.75 | R17: 3669.5659 | S17: =(Q17-Q16)/Q16 -> -0.0090850046 | T17: =(R17-R16)/R16 -> -0.014691062
B18: Long Term Provisions | C18: 37 | F18: Employee Benefit Expenses | G18: 1094 | J18: Cost of Equity (Re) | K18: =K33+K31*(K32-K33) -> 0.11402757 | L18: =_xlfn.FORMULATEXT(K18) -> =K33+K31*(K32-K33) | M18: = RF + Beta(Rm-Rf) | P18: 45401 | Q18: 18404.6 | R18: 3632.7605 | S18: =(Q18-Q17)/Q17 -> -0.0065395674 | T18: =(R18-R17)/R17 -> -0.010029911
B19: Total Non-Current Liabilities | C19: 621 | F19: Finance Costs | G19: 3 | J19: Tax Rate | K19: =G31 / G25 -> 0.26028664 | L19: =_xlfn.FORMULATEXT(K19) -> =G31 / G25 | M19: =Tax/EBT | P19: 45404 | Q19: 18643 | R19: 3697.8628 | S19: =(Q19-Q18)/Q18 -> 0.012953305 | T19: =(R19-R18)/R18 -> 0.017920888
B20: CURRENT LIABILITIES | F20: Depreciation And Amortisation Expenses | G20: 378 | J20: Weight of Debt | K20: =K13 / (K13 + C12) -> 0 | L20: =_xlfn.FORMULATEXT(K20) -> =K13 / (K13 + C12) | M20: =Debt/(Debt+Equity) | P20: 45405 | Q20: 18463.75 | R20: 3728.6821 | S20: =(Q20-Q19)/Q19 -> -0.0096148689 | T20: =(R20-R19)/R19 -> 0.0083343644
B21: Short Term Borrowings | C21: 0 | F21: Other Expenses | G21: 1417 | J21: Weight of Equity | K21: =C12 / (K13 + C12) -> 1 | L21: =_xlfn.FORMULATEXT(K21) -> =C12 / (K13 + C12) | M21: =Equity/(Debt+Equity) | P21: 45406 | Q21: 18586.199 | R21: 3773.3535 | S21: =(Q21-Q20)/Q20 -> 0.0066318716 | T21: =(R21-R20)/R20 -> 0.011980476
B22: Trade Payables | C22: 824 | F22: Total Expenses | G22: 6021 | J22: WACC | K22: =K21 * K18 + K20 * K17 -> 0.11402757 | L22: =_xlfn.FORMULATEXT(K22) -> =K21 * K18 + K20 * K17 | M22: =(Equity Weight×Cost of Equity)+(Debt Weight×Cost of Debt) | P22: 45407 | Q22: 18878.15 | R22: 3803.0356 | S22: =(Q22-Q21)/Q21 -> 0.015707955 | T22: =(R22-R21)/R21 -> 0.0078662465
B23: Other Current Liabilities | C23: 447 | F23: Profit/Loss Before Exceptional, ExtraOrdinary Items And Tax | G23: 2163 | P23: 45408 | Q23: 18994.65 | R23: 3973.7556 | S23: =(Q23-Q22)/Q22 -> 0.0061711554 | T23: =(R23-R22)/R22 -> 0.044890447
B24: Short Term Provisions | C24: 7 | F24: Exceptional Items | G24: 0 | P24: 45411 | Q24: 19096.9 | R24: 3946.9429 | S24: =(Q24-Q23)/Q23 -> 0.0053830946 | T24: =(R24-R23)/R23 -> -0.0067474567
B25: Total Current Liabilities | C25: 1278 | F25: Profit/Loss Before Tax | G25: 2163 | J25: Sale | K25: =G9 -> 7796 | L25: =_xlfn.FORMULATEXT(K25) -> =G9 | M25: = Revenue From Operations [Net] | P25: 45412 | Q25: 18970.6 | R25: 3959.9534 | S25: =(Q25-Q24)/Q24 -> -0.0066136796 | T25: =(R25-R24)/R24 -> 0.0032963482
B26: Total Capital And Liabilities | C26: 15470 | F26: Tax Expenses-Continued Operations | J26: Variable Cost | K26: =G14+G15+G17 -> 3129 | L26: =_xlfn.FORMULATEXT(K26) -> =G14+G15+G17 | M26: = Cost Of Materials Consumed + Purchase Of Stock-In Trade + Changes In Inventories | P26: 45414 | Q26: 19124.449 | R26: 3922.6038 | S26: =(Q26-Q25)/Q25 -> 0.008109897 | T26: =(R26-R25)/R25 -> -0.0094318306
B27: ASSETS | F27: Current Tax | G27: 514 | J27: Contribution | K27: =K25-K26 -> 4667 | L27: =_xlfn.FORMULATEXT(K27) -> =K25-K26 | M27: = Contribution =Sales - Variable cost | P27: 45415 | Q27: 19133.4 | R27: 3909.0488 | S27: =(Q27-Q26)/Q26 -> 0.00046804861 | T27: =(R27-R26)/R26 -> -0.0034555954
B28: NON-CURRENT ASSETS | F28: Less: MAT Credit Entitlement | G28: 0 | J28: EBIT | K28: =G25+G19 -> 2166 | L28: =_xlfn.FORMULATEXT(K28) -> =G25+G19 | M28: = Profit/Loss Before Tax + Finance Costs | P28: 45418 | Q28: 19203.301 | R28: 3920.9712 | S28: =(Q28-Q27)/Q27 -> 0.0036533177 | T28: =(R28-R27)/R27 -> 0.0030499397
B29: Tangible Assets | C29: 4735 | F29: Deferred Tax | G29: 49 | J29: EBT | K29: =G25 -> 2163 | L29: =_xlfn.FORMULATEXT(K29) -> =G25 | M29: = Profit/Loss Before Tax | P29: 45419 | Q29: 18846.301 | R29: 3869.9182 | S29: =(Q29-Q28)/Q28 -> -0.018590554 | T29: =(R29-R28)/R28 -> -0.013020493
B30: Intangible Assets | C30: 4 | F30: Other Direct Taxes | G30: 0 | P30: 45420 | Q30: 18850.85 | R30: 3885.6995 | S30: =(Q30-Q29)/Q29 -> 0.00024136451 | T30: =(R30-R29)/R29 -> 0.0040779286
B31: Capital Work-In-Progress | C31: 778 | F31: Total Tax Expenses | G31: 563 | J31: Beta | K31: ='DIVISLAB Beta Calc'!H7 -> 1.0740221 | P31: 45421 | Q31: 18437.051 | R31: 3749.7563 | S31: =(Q31-Q30)/Q30 -> -0.021951203 | T31: =(R31-R30)/R30 -> -0.034985494
B32: Fixed Assets | C32: 5517 | F32: Profit/Loss After Tax And Before ExtraOrdinary Items | G32: 1600 | J32: Market return (Rm) | K32: ='DIVISLAB Beta Calc'!H10*252 -> 0.11078641 | P32: 45422 | Q32: 18609.449 | R32: 3753.2688 | S32: =(Q32-Q31)/Q31 -> 0.0093506516 | T32: =(R32-R31)/R31 -> 0.00093671451
B33: Non-Current Investments | C33: 82 | F33: Profit/Loss From Continuing Operations | G33: 1600 | J33: Risk Free Rate (Rf) | K33: =6.7/100 -> 0.067 | L33: =6.7/100 | M33: = It is Standard | P33: 45425 | Q33: 18939 | R33: 3870.0173 | S33: =(Q33-Q32)/Q32 -> 0.017708787 | T33: =(R33-R32)/R32 -> 0.031105828
B34: Deferred Tax Assets [Net] | C34: 10 | F34: Profit/Loss For The Period | G34: 1600 | P34: 45426 | Q34: 18860.85 | R34: 3854.8796 | S34: =(Q34-Q33)/Q33 -> -0.0041264265 | T34: =(R34-R33)/R33 -> -0.0039115317
B35: Long Term Loans And Advances | C35: 0 | F35: Minority Interest | G35: 0 | P35: 45427 | Q35: 18886.551 | R35: 3851.2683 | S35: =(Q35-Q34)/Q34 -> 0.0013626731 | T35: =(R35-R34)/R34 -> -0.00093681994
B36: Other Non-Current Assets | C36: 186 | F36: Consolidated Profit/Loss After MI And Associates | G36: 1600 | P36: 45428 | Q36: 18996.15 | R36: 3889.459 | S36: =(Q36-Q35)/Q35 -> 0.0058030506 | T36: =(R36-R35)/R35 -> 0.0099163888
B37: Total Non-Current Assets | C37: 5795 | F37: OTHER ADDITIONAL INFORMATION | P37: 45429 | Q37: 18981.6 | R37: 3869.2754 | S37: =(Q37-Q36)/Q36 -> -0.00076598579 | T37: =(R37-R36)/R36 -> -0.0051893062
B38: CURRENT ASSETS | F38: EARNINGS PER SHARE | P38: 45433 | Q38: 19205.199 | R38: 3973.9534 | S38: =(Q38-Q37)/Q37 -> 0.011779809 | T38: =(R38-R37)/R37 -> 0.027053639
B39: Current Investments | C39: 0 | F39: Basic EPS (Rs.) | G39: 60 | P39: 45434 | Q39: 19317.4 | R39: 4015.5081 | S39: =(Q39-Q38)/Q38 -> 0.005842229 | T39: =(R39-R38)/R38 -> 0.010456763
B40: Inventories | C40: 3184 | F40: Diluted EPS (Rs.) | G40: 60 | P40: 45435 | Q40: 19216.35 | R40: 4069.3804 | S40: =(Q40-Q39)/Q39 -> -0.0052310756 | T40: =(R40-R39)/R39 -> 0.013416064
B41: Trade Receivables | C41: 2156 | F41: DIVIDEND AND DIVIDEND PERCENTAGE | P41: 45436 | Q41: 19119.5 | R41: 4078.6807 | S41: =(Q41-Q40)/Q40 -> -0.0050399588 | T41: =(R41-R40)/R40 -> 0.0022854322
B42: Cash And Cash Equivalents | C42: 3980 | F42: Equity Share Dividend | G42: 796 | P42: 45439 | Q42: 19111.949 | R42: 4210.1216 | S42: =(Q42-Q41)/Q41 -> -0.00039492566 | T42: =(R42-R41)/R41 -> 0.032226332
B43: Short Term Loans And Advances | C43: 0 | F43: Tax On Dividend | G43: 0 | P43: 45440 | Q43: 19215.75 | R43: 4345.5205 | S43: =(Q43-Q42)/Q42 -> 0.005431198 | T43: =(R43-R42)/R42 -> 0.032160336
B44: OtherCurrentAssets | C44: 355 | P44: 45441 | Q44: 19321.35 | R44: 4400.8276 | S44: =(Q44-Q43)/Q43 -> 0.0054954717 | T44: =(R44-R43)/R43 -> 0.012727389
B45: Total Current Assets | C45: 9675 | P45: 45442 | Q45: 18971 | R45: 4366.001 | S45: =(Q45-Q44)/Q44 -> -0.018132771 | T45: =(R45-R44)/R44 -> -0.0079136615
B46: Total Assets | C46: 15470 | P46: 45443 | Q46: 18796.301 | R46: 4261.521 | S46: =(Q46-Q45)/Q45 -> -0.0092087512 | T46: =(R46-R45)/R45 -> -0.023930361
B47: OTHER ADDITIONAL INFORMATION | P47: 45446 | Q47: 18864.15 | R47: 4276.0649 | S47: =(Q47-Q46)/Q46 -> 0.0036097321 | T47: =(R47-R46)/R46 -> 0.0034128531
B48: CONTINGENT LIABILITIES, COMMITMENTS | P48: 45447 | Q48: 18603.15 | R48: 4278.291 | S48: =(Q48-Q47)/Q47 -> -0.013835768 | T48: =(R48-R47)/R47 -> 0.00052058943
B49: Contingent Liabilities | C49: 1432 | P49: 45448 | Q49: 19281.25 | R49: 4454.9478 | S49: =(Q49-Q48)/Q48 -> 0.036450794 | T49: =(R49-R48)/R48 -> 0.041291426
B50: BONUS DETAILS | P50: 45449 | Q50: 19232.1 | R50: 4401.7178 | S50: =(Q50-Q49)/Q49 -> -0.0025491288 | T50: =(R50-R49)/R49 -> -0.011948508
B51: Bonus Equity Share Capital | C51: 39.67 | P51: 45450 | Q51: 19578 | R51: 4476.0708 | S51: =(Q51-Q50)/Q50 -> 0.017985576 | T51: =(R51-R50)/R50 -> 0.016891821
B52: NON-CURRENT INVESTMENTS | P52: 45453 | Q52: 19774.699 | R52: 4488.1421 | S52: =(Q52-Q51)/Q51 -> 0.010046952 | T52: =(R52-R51)/R51 -> 0.0026968494
B53: Non-Current Investments Quoted Market Value | C53: 0 | P53: 45454 | Q53: 19689.699 | R53: 4427.9863 | S53: =(Q53-Q52)/Q52 -> -0.0042984219 | T53: =(R53-R52)/R52 -> -0.013403266
B54: Non-Current Investments Unquoted Book Value | C54: 82 | P54: 45455 | Q54: 19739.1 | R54: 4405.1318 | S54: =(Q54-Q53)/Q53 -> 0.0025089459 | T54: =(R54-R53)/R53 -> -0.0051613737
B55: CURRENT INVESTMENTS | P55: 45456 | Q55: 19838.5 | R55: 4544.7847 | S55: =(Q55-Q54)/Q54 -> 0.0050357105 | T55: =(R55-R54)/R54 -> 0.031702305
B56: Current Investments Quoted Market Value | C56: 0 | P56: 45457 | Q56: 19895.65 | R56: 4539.9365 | S56: =(Q56-Q55)/Q55 -> 0.0028807818 | T56: =(R56-R55)/R55 -> -0.001066749
B57: Current Investments Unquoted Book Value | C57: 0 | P57: 45461 | Q57: 19826.65 | R57: 4516.0923 | S57: =(Q57-Q56)/Q56 -> -0.0034680947 | T57: =(R57-R56)/R56 -> -0.0052521083
P58: 45462 | Q58: 19644.5 | R58: 4432.1914 | S58: =(Q58-Q57)/Q57 -> -0.009187149 | T58: =(R58-R57)/R57 -> -0.018578203
P59: 45463 | Q59: 19544.551 | R59: 4456.2832 | S59: =(Q59-Q58)/Q58 -> -0.0050878983 | T59: =(R59-R58)/R58 -> 0.00543564
P60: 45464 | Q60: 19528.4 | R60: 4474.1914 | S60: =(Q60-Q59)/Q59 -> -0.00082633726 | T60: =(R60-R59)/R59 -> 0.0040186412
P61: 45467 | Q61: 19521.15 | R61: 4471.6191 | S61: =(Q61-Q60)/Q60 -> -0.00037125417 | T61: =(R61-R60)/R60 -> -0.00057491184
P62: 45468 | Q62: 19532.301 | R62: 4491.1592 | S62: =(Q62-Q61)/Q61 -> 0.00057119537 | T62: =(R62-R61)/R61 -> 0.0043697905
P63: 45469 | Q63: 19545.35 | R63: 4497.1455 | S63: =(Q63-Q62)/Q62 -> 0.00066806406 | T63: =(R63-R62)/R62 -> 0.0013329138
P64: 45470 | Q64: 19514.801 | R64: 4474.3896 | S64: =(Q64-Q63)/Q63 -> -0.0015629717 | T64: =(R64-R63)/R63 -> -0.0050600674
P65: 45471 | Q65: 19731.551 | R65: 4547.7036 | S65: =(Q65-Q64)/Q64 -> 0.011106954 | T65: =(R65-R64)/R64 -> 0.016385244
P66: 45474 | Q66: 19758.25 | R66: 4553.2935 | S66: =(Q66-Q65)/Q65 -> 0.0013531232 | T66: =(R66-R65)/R65 -> 0.0012291574
P67: 45475 | Q67: 19786.4 | R67: 4522.9688 | S67: =(Q67-Q66)/Q66 -> 0.0014247411 | T67: =(R67-R66)/R66 -> -0.0066599501
P68: 45476 | Q68: 19915.301 | R68: 4510.7988 | S68: =(Q68-Q67)/Q67 -> 0.0065145953 | T68: =(R68-R67)/R67 -> -0.0026906933
P69: 45477 | Q69: 20192.6 | R69: 4495.8589 | S69: =(Q69-Q68)/Q68 -> 0.013923909 | T69: =(R69-R68)/R68 -> -0.0033120389
... P252: 45744 | Q252: 21137.449 | R252: 5749.2715 | S252: =(Q252-Q251)/Q251 -> -0.0064723948 | T252: =(R252-R251)/R251 -> -0.016551277

Sheet Torrent Beta Calc
C2: TORNTPHARM.NS
A3: Price | B3: Close | C3: Close | D3: Return | E3: Return | H3: Covariance(Market/company) | I3: variance (Market)
A4: Ticker | B4: ^CNXPHARMA | C4: TORNTPHARM.NS | D4: Nifty | E4: Company | H4: =_xlfn.COVARIANCE.S(D7:D252,E7:E252) -> 8.4229259e-05 | I4: =_xlfn.VAR.S(D7:D252) -> 0.00010123143
A5: Date
A6: 45383 | B6: 19207.9 | C6: 2626.0349 | H6: Beta
A7: 45384 | B7: 19185.15 | C7: 2619.3601 | D7: =(B7-B6)/B6 -> -0.0011844085 | E7: =(C7-C6)/C6 -> -0.0025417806 | H7: =H4/I4 -> 0.83204651
A8: 45385 | B8: 19153.051 | C8: 2540.9326 | D8: =(B8-B7)/B7 -> -0.0016731487 | E8: =(C8-C7)/C7 -> -0.029941469
A9: 45386 | B9: 19125.199 | C9: 2490.7749 | D9: =(B9-B8)/B8 -> -0.001454158 | E9: =(C9-C8)/C8 -> -0.019739884 | H9: Market Return
A10: 45387 | B10: 19160.75 | C10: 2529.5959 | D10: =(B10-B9)/B9 -> 0.001858845 | E10: =(C10-C9)/C9 -> 0.015585931 | H10: =AVERAGE(D7:D252) -> 0.00043962859
A11: 45390 | B11: 19218.85 | C11: 2549.4236 | D11: =(B11-B10)/B10 -> 0.00303222 | E11: =(C11-C10)/C10 -> 0.0078382624
A12: 45391 | B12: 19182.301 | C12: 2530.5774 | D12: =(B12-B11)/B11 -> -0.0019017178 | E12: =(C12-C11)/C11 -> -0.0073923343
A13: 45392 | B13: 19117 | C13: 2531.4119 | D13: =(B13-B12)/B12 -> -0.0034042205 | E13: =(C13-C12)/C12 -> 0.00032975583
A14: 45394 | B14: 18788.65 | C14: 2530.1846 | D14: =(B14-B13)/B13 -> -0.017175792 | E14: =(C14-C13)/C13 -> -0.00048482625
A15: 45397 | B15: 18617.65 | C15: 2473.4014 | D15: =(B15-B14)/B14 -> -0.0091012391 | E15: =(C15-C14)/C14 -> -0.022442317
A16: 45398 | B16: 18695.6 | C16: 2490.824 | D16: =(B16-B15)/B15 -> 0.0041868451 | E16: =(C16-C15)/C15 -> 0.0070439871
A17: 45400 | B17: 18525.75 | C17: 2499.9036 | D17: =(B17-B16)/B16 -> -0.0090850046 | E17: =(C17-C16)/C16 -> 0.0036452154
A18: 45401 | B18: 18404.6 | C18: 2492.5908 | D18: =(B18-B17)/B17 -> -0.0065395674 | E18: =(C18-C17)/C17 -> -0.0029252105
A19: 45404 | B19: 18643 | C19: 2544.123 | D19: =(B19-B18)/B18 -> 0.012953305 | E19: =(C19-C18)/C18 -> 0.020674162
A20: 45405 | B20: 18463.75 | C20: 2588.7839 | D20: =(B20-B19)/B19 -> -0.0096148689 | E20: =(C20-C19)/C19 -> 0.017554532
A21: 45406 | B21: 18586.199 | C21: 2636.9299 | D21: =(B21-B20)/B20 -> 0.0066318716 | E21: =(C21-C20)/C20 -> 0.01859792
A22: 45407 | B22: 18878.15 | C22: 2644.6355 | D22: =(B22-B21)/B21 -> 0.015707955 | E22: =(C22-C21)/C21 -> 0.0029221734
... A252: 45744 | B252: 21137.449 | C252: 3199.8877 | D252: =(B252-B251)/B251 -> -0.0064723948 | E252: =(C252-C251)/C251 -> -0.001608336

Sheet Torrent Pharmaceuticals
C2: Torrent Pharmaceuticals | P2: TORNTPHARM.NS
P3: Price | Q3: Close | R3: Close | S3: Return | T3: Return | W3: Covariance(Market/company) | X3: variance (Market)
B4: Balance Sheet of Torrent Pharmaceuticals (in Rs. Cr.) | C4: 46105 | F4: Profit & Loss account of Torrent Pharmaceuticals (in Rs. Cr.) | G4: 46105 | P4: Ticker | Q4: ^CNXPHARMA | R4: TORNTPHARM.NS | S4: Nifty | T4: Company | W4: =_xlfn.COVARIANCE.S(S7:S252,T7:T252) -> 8.4229259e-05 | X4: =_xlfn.VAR.S(S7:S252) -> 0.00010123143
C5: 12 mths | G5: 12 mths | P5: Date
B6: EQUITIES AND LIABILITIES | F6: INCOME | P6: 45383 | Q6: 19207.9 | R6: 2626.0349 | W6: Beta
B7: SHAREHOLDER'S FUNDS | F7: Revenue From Operations [Gross] | G7: 10562.31 | P7: 45384 | Q7: 19185.15 | R7: 2619.3601 | S7: =(Q7-Q6)/Q6 -> -0.0011844085 | T7: =(R7-R6)/R6 -> -0.0025417806 | W7: =W4/X4 -> 0.83204651
B8: Equity Share Capital | C8: 169.23 | F8: Less: Excise/Sevice Tax/Other Levies | G8: 0 | P8: 45385 | Q8: 19153.051 | R8: 2540.9326 | S8: =(Q8-Q7)/Q7 -> -0.0016731487 | T8: =(R8-R7)/R7 -> -0.029941469
B9: Total Share Capital | C9: 169.23 | F9: Revenue From Operations [Net] | G9: 10562.31 | P9: 45386 | Q9: 19125.199 | R9: 2490.7749 | S9: =(Q9-Q8)/Q8 -> -0.001454158 | T9: =(R9-R8)/R8 -> -0.019739884 | W9: Market Return
B10: Reserves and Surplus | C10: 6686.92 | F10: Total Operating Revenues | G10: 10727.84 | P10: 45387 | Q10: 19160.75 | R10: 2529.5959 | S10: =(Q10-Q9)/Q9 -> 0.001858845 | T10: =(R10-R9)/R9 -> 0.015585931 | W10: =AVERAGE(S7:S252) -> 0.00043962859
B11: Total Reserves and Surplus | C11: 6686.92 | F11: Other Income | G11: 57.91 | P11: 45390 | Q11: 19218.85 | R11: 2549.4236 | S11: =(Q11-Q10)/Q10 -> 0.00303222 | T11: =(R11-R10)/R10 -> 0.0078382624
B12: Total Shareholders Funds | C12: 6856.15 | F12: Total Revenue | G12: 10785.75 | P12: 45391 | Q12: 19182.301 | R12: 2530.5774 | S12: =(Q12-Q11)/Q11 -> -0.0019017178 | T12: =(R12-R11)/R11 -> -0.0073923343
B13: Minority Interest | C13: 0 | F13: EXPENSES | J13: Total Debt | K13: =C15 + C21 -> 3937.42 | L13: =_xlfn.FORMULATEXT(K13) -> =C15 + C21 | M13: = Longterm borrowings + shortterm borrowings | P13: 45392 | Q13: 19117 | R13: 2531.4119 | S13: =(Q13-Q12)/Q12 -> -0.0034042205 | T13: =(R13-R12)/R12 -> 0.00032975583
B14: NON-CURRENT LIABILITIES | F14: Cost Of Materials Consumed | G14: 1657.59 | J14: DOL | K14: =K27 / K28 -> 2.9109611 | L14: =_xlfn.FORMULATEXT(K14) -> =K27 / K28 | M14: =Contribution/EBIT | P14: 45394 | Q14: 18788.65 | R14: 2530.1846 | S14: =(Q14-Q13)/Q13 -> -0.017175792 | T14: =(R14-R13)/R13 -> -0.00048482625
B15: Long Term Borrowings | C15: 1603.78 | F15: Purchase Of Stock-In Trade | G15: 1183.63 | J15: DFL | K15: =K28 / K29 -> 1.1503161 | L15: =_xlfn.FORMULATEXT(K15) -> =K28 / K29 | M15: =EBIT/EBT | P15: 45397 | Q15: 18617.65 | R15: 2473.4014 | S15: =(Q15-Q14)/Q14 -> -0.0091012391 | T15: =(R15-R14)/R14 -> -0.022442317
B16: Deferred Tax Liabilities [Net] | C16: 656.05 | F16: Operating And Direct Expenses | G16: 0 | J16: DTL | K16: =K14 * K15 -> 3.3485254 | L16: =_xlfn.FORMULATEXT(K16) -> =K14 * K15 | M16: =DOL * DFL | P16: 45398 | Q16: 18695.6 | R16: 2490.824 | S16: =(Q16-Q15)/Q15 -> 0.0041868451 | T16: =(R16-R15)/R15 -> 0.0070439871
B17: Other Long Term Liabilities | C17: 74.66 | F17: Changes In Inventories Of FGWIP And Stock In Trade | G17: -155.01 | J17: Cost of Debt (Rd) | K17: =G19 / (C15 + C21) -> 0.08979484 | L17: =_xlfn.FORMULATEXT(K17) -> =G19 / (C15 + C21) | M17: =Interest/Total Debt | P17: 45400 | Q17: 18525.75 | R17: 2499.9036 | S17: =(Q17-Q16)/Q16 -> -0.0090850046 | T17: =(R17-R16)/R16 -> 0.0036452154
B18: Long Term Provisions | C18: 444.69 | F18: Employee Benefit Expenses | G18: 1984.4 | J18: Cost of Equity (Re) | K18: =K33+K31*(K32-K33) -> 0.10343233 | L18: =_xlfn.FORMULATEXT(K18) -> =K33+K31*(K32-K33) | M18: = RF + Beta(Rm-Rf) | P18: 45401 | Q18: 18404.6 | R18: 2492.5908 | S18: =(Q18-Q17)/Q17 -> -0.0065395674 | T18: =(R18-R17)/R17 -> -0.0029252105
B19: Total Non-Current Liabilities | C19: 2779.18 | F19: Finance Costs | G19: 353.56 | J19: Tax Rate | K19: =G31 / G25 -> 0.29578974 | L19: =_xlfn.FORMULATEXT(K19) -> =G31 / G25 | M19: =Tax/EBT | P19: 45404 | Q19: 18643 | R19: 2544.123 | S19: =(Q19-Q18)/Q18 -> 0.012953305 | T19: =(R19-R18)/R18 -> 0.020674162
B20: CURRENT LIABILITIES | F20: Depreciation And Amortisation Expenses | G20: 808.27 | J20: Weight of Debt | K20: =K13 / (K13 + C12) -> 0.36479311 | L20: =_xlfn.FORMULATEXT(K20) -> =K13 / (K13 + C12) | M20: =Debt/(Debt+Equity) | P20: 45405 | Q20: 18463.75 | R20: 2588.7839 | S20: =(Q20-Q19)/Q19 -> -0.0096148689 | T20: =(R20-R19)/R19 -> 0.017554532
B21: Short Term Borrowings | C21: 2333.64 | F21: Other Expenses | G21: 2689.58 | J21: Weight of Equity | K21: =C12 / (K13 + C12) -> 0.63520689 | L21: =_xlfn.FORMULATEXT(K21) -> =C12 / (K13 + C12) | M21: =Equity/(Debt+Equity) | P21: 45406 | Q21: 18586.199 | R21: 2636.9299 | S21: =(Q21-Q20)/Q20 -> 0.0066318716 | T21: =(R21-R20)/R20 -> 0.01859792
B22: Trade Payables | C22: 2089.32 | F22: Total Expenses | G22: 8522.02 | J22: WACC | K22: =K21 * K18 + K20 * K17 -> 0.098457465 | L22: =_xlfn.FORMULATEXT(K22) -> =K21 * K18 + K20 * K17 | M22: =(Equity Weight×Cost of Equity)+(Debt Weight×Cost of Debt) | P22: 45407 | Q22: 18878.15 | R22: 2644.6355 | S22: =(Q22-Q21)/Q21 -> 0.015707955 | T22: =(R22-R21)/R21 -> 0.0029221734
B23: Other Current Liabilities | C23: 602.15 | F23: Profit/Loss Before Exceptional, ExtraOrdinary Items And Tax | G23: 2263.73 | P23: 45408 | Q23: 18994.65 | R23: 2641.3965 | S23: =(Q23-Q22)/Q22 -> 0.0061711554 | T23: =(R23-R22)/R22 -> -0.0012247486
B24: Short Term Provisions | C24: 400.14 | F24: Exceptional Items | G24: 88.38 | P24: 45411 | Q24: 19096.9 | R24: 2637.9116 | S24: =(Q24-Q23)/Q23 -> 0.0053830946 | T24: =(R24-R23)/R23 -> -0.0013193261
B25: Total Current Liabilities | C25: 5425.25 | F25: Profit/Loss Before Tax | G25: 2352.11 | J25: Sale | K25: =G9 -> 10562.31 | L25: =_xlfn.FORMULATEXT(K25) -> =G9 | M25: = Revenue From Operations [Net] | P25: 45412 | Q25: 18970.6 | R25: 2593.8396 | S25: =(Q25-Q24)/Q24 -> -0.0066136796 | T25: =(R25-R24)/R24 -> -0.016707164
B26: Total Capital And Liabilities | C26: 15060.58 | F26: Tax Expenses-Continued Operations | J26: Variable Cost | K26: =G14+G15+G17 -> 2686.21 | L26: =_xlfn.FORMULATEXT(K26) -> =G14+G15+G17 | M26: = Cost Of Materials Consumed + Purchase Of Stock-In Trade + Changes In Inventories | P26: 45414 | Q26: 19124.449 | R26: 2620.7834 | S26: =(Q26-Q25)/Q25 -> 0.008109897 | T26: =(R26-R25)/R25 -> 0.010387631
B27: ASSETS | F27: Current Tax | G27: 461.73 | J27: Contribution | K27: =K25-K26 -> 7876.1 | L27: =_xlfn.FORMULATEXT(K27) -> =K25-K26 | M27: = Contribution =Sales - Variable cost | P27: 45415 | Q27: 19133.4 | R27: 2684.2905 | S27: =(Q27-Q26)/Q26 -> 0.00046804861 | T27: =(R27-R26)/R26 -> 0.024232098
B28: NON-CURRENT ASSETS | F28: Less: MAT Credit Entitlement | G28: 0 | J28: EBIT | K28: =G25+G19 -> 2705.67 | L28: =_xlfn.FORMULATEXT(K28) -> =G25+G19 | M28: = Profit/Loss Before Tax + Finance Costs | P28: 45418 | Q28: 19203.301 | R28: 2667.1133 | S28: =(Q28-Q27)/Q27 -> 0.0036533177 | T28: =(R28-R27)/R27 -> -0.0063991755
B29: Tangible Assets | C29: 3296.97 | F29: Deferred Tax | G29: 234 | J29: EBT | K29: =G25 -> 2352.11 | L29: =_xlfn.FORMULATEXT(K29) -> =G25 | M29: = Profit/Loss Before Tax | P29: 45419 | Q29: 18846.301 | R29: 2571.0671 | S29: =(Q29-Q28)/Q28 -> -0.018590554 | T29: =(R29-R28)/R28 -> -0.036011272
B30: Intangible Assets | C30: 4503.11 | F30: Other Direct Taxes | G30: 0 | P30: 45420 | Q30: 18850.85 | R30: 2539.8533 | S30: =(Q30-Q29)/Q29 -> 0.00024136451 | T30: =(R30-R29)/R29 -> -0.012140433
B31: Capital Work-In-Progress | C31: 280.8 | F31: Total Tax Expenses | G31: 695.73 | J31: Beta | K31: ='Torrent Beta Calc'!H7 -> 0.83204651 | P31: 45421 | Q31: 18437.051 | R31: 2477.8184 | S31: =(Q31-Q30)/Q30 -> -0.021951203 | T31: =(R31-R30)/R30 -> -0.024424605
B32: Fixed Assets | C32: 8160.59 | F32: Profit/Loss After Tax And Before ExtraOrdinary Items | G32: 1656.38 | J32: Market return (Rm) | K32: ='Torrent Beta Calc'!H10*252 -> 0.11078641 | P32: 45422 | Q32: 18609.449 | R32: 2551.9753 | S32: =(Q32-Q31)/Q31 -> 0.0093506516 | T32: =(R32-R31)/R31 -> 0.029928337
B33: Non-Current Investments | C33: 31.8 | F33: Profit/Loss From Continuing Operations | G33: 1656.38 | J33: Risk Free Rate (Rf) | K33: =6.7/100 -> 0.067 | L33: =6.7/100 | M33: = It is Standard | P33: 45425 | Q33: 18939 | R33: 2556.5889 | S33: =(Q33-Q32)/Q32 -> 0.017708787 | T33: =(R33-R32)/R32 -> 0.0018078252
B34: Deferred Tax Assets [Net] | C34: 555.13 | F34: Profit/Loss For The Period | G34: 1656.38 | P34: 45426 | Q34: 18860.85 | R34: 2582.1587 | S34: =(Q34-Q33)/Q33 -> -0.0041264265 | T34: =(R34-R33)/R33 -> 0.010001539
B35: Long Term Loans And Advances | C35: 2.51 | F35: Minority Interest | G35: 0 | P35: 45427 | Q35: 18886.551 | R35: 2600.1216 | S35: =(Q35-Q34)/Q34 -> 0.0013626731 | T35: =(R35-R34)/R34 -> 0.0069565402
B36: Other Non-Current Assets | C36: 361.04 | F36: Consolidated Profit/Loss After MI And Associates | G36: 1656.38 | P36: 45428 | Q36: 18996.15 | R36: 2650.1814 | S36: =(Q36-Q35)/Q35 -> 0.0058030506 | T36: =(R36-R35)/R35 -> 0.019252874
B37: Total Non-Current Assets | C37: 9449.1 | F37: OTHER ADDITIONAL INFORMATION | P37: 45429 | Q37: 18981.6 | R37: 2648.9541 | S37: =(Q37-Q36)/Q36 -> -0.00076598579 | T37: =(R37-R36)/R36 -> -0.00046309846
B38: CURRENT ASSETS | F38: EARNINGS PER SHARE | P38: 45433 | Q38: 19205.199 | R38: 2632.2676 | S38: =(Q38-Q37)/Q37 -> 0.011779809 | T38: =(R38-R37)/R37 -> -0.0062992875
B39: Current Investments | C39: 141.04 | F39: Basic EPS (Rs.) | G39: 49 | P39: 45434 | Q39: 19317.4 | R39: 2614.6484 | S39: =(Q39-Q38)/Q38 -> 0.005842229 | T39: =(R39-R38)/R38 -> -0.0066935219
B40: Inventories | C40: 2279.07 | F40: Diluted EPS (Rs.) | G40: 49 | P40: 45435 | Q40: 19216.35 | R40: 2643.2612 | S40: =(Q40-Q39)/Q39 -> -0.0052310756 | T40: =(R40-R39)/R39 -> 0.010943266
B41: Trade Receivables | C41: 1844.3 | F41: DIVIDEND AND DIVIDEND PERCENTAGE | P41: 45436 | Q41: 19119.5 | R41: 2564.3923 | S41: =(Q41-Q40)/Q40 -> -0.0050399588 | T41: =(R41-R40)/R40 -> -0.029837723
B42: Cash And Cash Equivalents | C42: 839.04 | F42: Equity Share Dividend | G42: 1015.34 | P42: 45439 | Q42: 19111.949 | R42: 2606.3052 | S42: =(Q42-Q41)/Q41 -> -0.00039492566 | T42: =(R42-R41)/R41 -> 0.016344161
B43: Short Term Loans And Advances | C43: 3.05 | F43: Tax On Dividend | G43: 0 | P43: 45440 | Q43: 19215.75 | R43: 2617.5439 | S43: =(Q43-Q42)/Q42 -> 0.005431198 | T43: =(R43-R42)/R42 -> 0.0043121464
B44: OtherCurrentAssets | C44: 504.98 | P44: 45441 | Q44: 19321.35 | R44: 2664.1687 | S44: =(Q44-Q43)/Q43 -> 0.0054954717 | T44: =(R44-R43)/R43 -> 0.017812406
B45: Total Current Assets | C45: 5611.48 | P45: 45442 | Q45: 18971 | R45: 2609.0535 | S45: =(Q45-Q44)/Q44 -> -0.018132771 | T45: =(R45-R44)/R44 -> -0.020687592
B46: Total Assets | C46: 15060.58 | P46: 45443 | Q46: 18796.301 | R46: 2646.3533 | S46: =(Q46-Q45)/Q45 -> -0.0092087512 | T46: =(R46-R45)/R45 -> 0.014296298
B47: OTHER ADDITIONAL INFORMATION | P47: 45446 | Q47: 18864.15 | R47: 2628.5867 | S47: =(Q47-Q46)/Q46 -> 0.0036097321 | T47: =(R47-R46)/R46 -> -0.0067136167
B48: CONTINGENT LIABILITIES, COMMITMENTS | P48: 45447 | Q48: 18603.15 | R48: 2644.3411 | S48: =(Q48-Q47)/Q47 -> -0.013835768 | T48: =(R48-R47)/R47 -> 0.0059934849
B49: Contingent Liabilities | C49: 575.06 | P49: 45448 | Q49: 19281.25 | R49: 2729.1482 | S49: =(Q49-Q48)/Q48 -> 0.036450794 | T49: =(R49-R48)/R48 -> 0.032071176
B50: BONUS DETAILS | P50: 45449 | Q50: 19232.1 | R50: 2730.719 | S50: =(Q50-Q49)/Q49 -> -0.0025491288 | T50: =(R50-R49)/R49 -> 0.00057556449
B51: Bonus Equity Share Capital | C51: 162.41 | P51: 45450 | Q51: 19578 | R51: 2792.5085 | S51: =(Q51-Q50)/Q50 -> 0.017985576 | T51: =(R51-R50)/R50 -> 0.022627576
B52: NON-CURRENT INVESTMENTS | P52: 45453 | Q52: 19774.699 | R52: 2811.1582 | S52: =(Q52-Q51)/Q51 -> 0.010046952 | T52: =(R52-R51)/R51 -> 0.0066784606
B53: Non-Current Investments Quoted Market Value | C53: 0 | P53: 45454 | Q53: 19689.699 | R53: 2798.447 | S53: =(Q53-Q52)/Q52 -> -0.0042984219 | T53: =(R53-R52)/R52 -> -0.0045216885
B54: Non-Current Investments Unquoted Book Value | C54: 31.8 | P54: 45455 | Q54: 19739.1 | R54: 2840.1636 | S54: =(Q54-Q53)/Q53 -> 0.0025089459 | T54: =(R54-R53)/R53 -> 0.014907037
B55: CURRENT INVESTMENTS | P55: 45456 | Q55: 19838.5 | R55: 2821.9065 | S55: =(Q55-Q54)/Q54 -> 0.0050357105 | T55: =(R55-R54)/R54 -> -0.0064281791
B56: Current Investments Quoted Market Value | C56: 0 | P56: 45457 | Q56: 19895.65 | R56: 2828.9739 | S56: =(Q56-Q55)/Q55 -> 0.0028807818 | T56: =(R56-R55)/R55 -> 0.0025044709
B57: Current Investments Unquoted Book Value | C57: 141.04 | P57: 45461 | Q57: 19826.65 | R57: 2833.6362 | S57: =(Q57-Q56)/Q56 -> -0.0034680947 | T57: =(R57-R56)/R56 -> 0.0016480723
P58: 45462 | Q58: 19644.5 | R58: 2832.3601 | S58: =(Q58-Q57)/Q57 -> -0.009187149 | T58: =(R58-R57)/R57 -> -0.00045034823
P59: 45463 | Q59: 19544.551 | R59: 2805.4163 | S59: =(Q59-Q58)/Q58 -> -0.0050878983 | T59: =(R59-R58)/R58 -> -0.0095128609
P60: 45464 | Q60: 19528.4 | R60: 2784.9075 | S60: =(Q60-Q59)/Q59 -> -0.00082633726 | T60: =(R60-R59)/R59 -> -0.0073104264
P61: 45467 | Q61: 19521.15 | R61: 2793.9565 | S61: =(Q61-Q60)/Q60 -> -0.00037125417 | T61: =(R61-R60)/R60 -> 0.003249326
P62: 45468 | Q62: 19532.301 | R62: 2784.1204 | S62: =(Q62-Q61)/Q61 -> 0.00057119537 | T62: =(R62-R61)/R61 -> -0.0035205206
P63: 45469 | Q63: 19545.35 | R63: 2744.8735 | S63: =(Q63-Q62)/Q62 -> 0.00066806406 | T63: =(R63-R62)/R62 -> -0.01409667
P64: 45470 | Q64: 19514.801 | R64: 2726.3318 | S64: =(Q64-Q63)/Q63 -> -0.0015629717 | T64: =(R64-R63)/R63 -> -0.0067550464
P65: 45471 | Q65: 19731.551 | R65: 2745.6113 | S65: =(Q65-Q64)/Q64 -> 0.011106954 | T65: =(R65-R64)/R64 -> 0.0070716048
P66: 45474 | Q66: 19758.25 | R66: 2735.6765 | S66: =(Q66-Q65)/Q65 -> 0.0013531232 | T66: =(R66-R65)/R65 -> -0.0036184344
P67: 45475 | Q67: 19786.4 | R67: 2773.4971 | S67: =(Q67-Q66)/Q66 -> 0.0014247411 | T67: =(R67-R66)/R66 -> 0.013824937
P68: 45476 | Q68: 19915.301 | R68: 2791.0549 | S68: =(Q68-Q67)/Q67 -> 0.0065145953 | T68: =(R68-R67)/R67 -> 0.0063305859
P69: 45477 | Q69: 20192.6 | R69: 2823.3181 | S69: =(Q69-Q68)/Q68 -> 0.013923909 | T69: =(R69-R68)/R68 -> 0.011559494
... P252: 45744 | Q252: 21137.449 | R252: 3199.8877 | S252: =(Q252-Q251)/Q251 -> -0.0064723948 | T252: =(R252-R251)/R251 -> -0.001608336

Sheet Nifty Pharma
C2: ^CNXPHARMA
A3: Price | B3: Close
A4: Ticker | B4: ^CNXPHARMA
A5: Date
A6: 45734 | B6: 21041.301
A7: 45735 | B7: 21145.65
A8: 45736 | B8: 21340.6
A9: 45737 | B9: 21625.9
A10: 45740 | B10: 21771.15
A11: 45741 | B11: 21542.5
A12: 45742 | B12: 21360.6
A13: 45743 | B13: 21275.15
A14: 45744 | B14: 21137.449
A15: 45748 | B15: 20771.801
A16: 45749 | B16: 20952.85
A17: 45750 | B17: 21423.551
... A201: 46022 | B201: 22723.65
A202: 46023
A203: 46024 | B203: 22790.9
A204: 46027 | B204: 22743.4
A205: 46028 | B205: 23126.85
A206: 46029 | B206: 23286.25
A207: 46030 | B207: 22962.551
A208: 46031 | B208: 22761
A209: 46034 | B209: 22668.449
A210: 46035 | B210: 22562.301
A211: 46036 | B211: 22505.4
A212: 46037
A213: 46038 | B213: 22217.051
A214: 46041 | B214: 22136.25
A215: 46042 | B215: 21714.301
A216: 46043 | B216: 21584.4
A217: 46044 | B217: 21928
A218: 46045 | B218: 21722.25
A219: 46049 | B219: 21788.449
A220: 46050 | B220: 21739.85
A221: 46051 | B221: 21564
A222: 46052 | B222: 21715.1
A223: 46055 | B223: 21549.551
A224: 46056 | B224: 22200.25
... A254: 46099 | B254: 22632.6

Sheet Comparative Analysis
A2: Items Company | B2: DOL | C2: DFL | D2: DTL | E2: WACC | I2: COMPANY ITEMS | J2: Lupin | K2: Torrent | L2: Sun Pharma
A3: Sun Pharma | B3: ='Sun Pharmaceutical Industries'!K$14 -> 3.2751776 | C3: ='Sun Pharmaceutical Industries'!$K$15 -> 1.0215072 | D3: ='Sun Pharmaceutical Industries'!$K$16 -> 3.3456176 | E3: ='Sun Pharmaceutical Industries'!$K$22 -> 0.10864506 | I3: Total Risk (DTL) Detail | J3: 5.37 (Extreme): The highest in the group. A 1% change in sales causes a massive 5.37% swing in bottom-line profit. | K3: 3.35 (Moderate-High): High fixed costs make their profits quite sensitive to market changes. | L3: 3.35 (Moderate-High): Similar sensitivity to Torrent, mainly due to large-scale operations and fixed assets.
A4: Dr. Reddy | B4: ='Dr. Reddy''s Laboratories'!$K$14 -> 2.6786229 | C4: ='Dr. Reddy''s Laboratories'!$K$15 -> 1.0238092 | D4: ='Dr. Reddy''s Laboratories'!$K$16 -> 2.7423987 | E4: ='Dr. Reddy''s Laboratories'!$K$22 -> 0.10264916 | I4: Debt Usage (DFL) Detail | J4: 1.13 (Moderate): Uses a fair amount of debt, which adds to the pressure on their profits. | K4: 1.15 (Highest): They are the most "leveraged" company, meaning they use more borrowed money than any peer. | L4: 1.02 (Low): Despite being a giant, they carry almost no debt risk. They are mostly self-funded.
A5: Cipla | B5: ='CIPLA '!$K$14 -> 2.8708031 | C5: ='CIPLA '!$K$15 -> 1.0157632 | D5: ='CIPLA '!$K$16 -> 2.9160561 | E5: ='CIPLA '!$K$22 -> 0.11117743 | I5: Cost of Money (WACC) Detail | J5: 12.24% (Highest): Investors see the high risk and demand a higher return, making their capital expensive. | K5: 9.85% (Lowest): Interestingly, their smart use of "cheaper" debt actually lowers their overall cost of capital. | L5: 10.86% (Average): Their cost of money is the "Gold Standard" or the industry benchmark.
A6: Lupin | B6: =LUPIN!$K$14 -> 4.7598541 | C6: =LUPIN!$K$15 -> 1.1286438 | D6: =LUPIN!$K$16 -> 5.3721798 | E6: =LUPIN!$K$22 -> 0.12243337 | I6: Why this "Personality"? | J6: The Aggressive Racer: Like a car with a massive turbocharger; it's the fastest when winning but the most likely to crash if sales slip. | K6: The Efficiency Expert: They use debt as a tool better than anyone else to keep their total "fuel costs" (WACC) at rock bottom. | L6: The Heavyweight Giant: They have the muscle (fixed assets) to dominate the market but play it very safe with their bank balance.
A7: Divis | B7: ='Divis Labs'!$K$14 -> 2.154663 | C7: ='Divis Labs'!$K$15 -> 1.001387 | D7: ='Divis Labs'!$K$16 -> 2.1576514 | E7: ='Divis Labs'!$K$22 -> 0.11402757
A8: Torrent | B8: ='Torrent Pharmaceuticals'!$K$14 -> 2.9109611 | C8: ='Torrent Pharmaceuticals'!$K$15 -> 1.1503161 | D8: ='Torrent Pharmaceuticals'!$K$16 -> 3.3485254 | E8: ='Torrent Pharmaceuticals'!$K$22 -> 0.098457465 | I8: COMPANY ITEMS | J8: Cipla | K8: Dr. Reddy | L8: Divis Labs
I9: Total Risk (DTL) Detail | J9: 2.92 (Moderate): A balanced cost structure. Their profits are more stable than Sun or Lupin. | K9: 2.74 (Low-Moderate): Lower sensitivity. They have optimized their costs so that a drop in sales won't hurt as much. | L9: 2.16 (Lowest): The most stable profit machine. Their earnings don't fluctuate wildly with sales.
I10: Debt Usage (DFL) Detail | J10: 1.02 (Low): Very conservative. They prefer using their own cash over taking bank loans. | K10: 1.02 (Low): Like Cipla and Sun, they avoid debt. Their financial risk is almost zero. | L10: 1.00 (Zero Debt): They have effectively no debt. They are essentially their own bank.
A11: Row Labels | B11: Sum of DOL | C11: Sum of DTL | D11: Sum of WACC | E11: Sum of DFL | I11: Cost of Money (WACC) Detail | J11: 11.12% (Moderate): A slightly higher cost of equity compared to Sun Pharma makes their fuel a bit pricier. | K11: 10.26% (Good): They enjoy a very healthy trust level from the market, keeping their capital costs low. | L11: 11.40% (Moderate): Because they have no "cheap" debt, they rely on "expensive" equity, which keeps their WACC slightly higher.
A12: Cipla | B12: 2.8708031 | C12: 2.9160561 | D12: 0.11117743 | E12: 1.0157632 | I12: Why this "Personality"? | J12: The Balanced Player: They sit right in the middle of the pack—not too risky, not too expensive, and very stable. | K12: The Solid Performer: They are highly efficient and very safe. They offer a "premium" feel with very little financial stress. | L12: The Safety Specialist: They are the "Fort Knox" of the group. Perfect for investors who hate risk and want a company that is debt-proof.
A13: Divis | B13: 2.154663 | C13: 2.1576514 | D13: 0.11402757 | E13: 1.001387
A14: Dr. Reddy | B14: 2.6786229 | C14: 2.7423987 | D14: 0.10264916 | E14: 1.0238092
A15: Lupin | B15: 4.7598541 | C15: 5.3721798 | D15: 0.12243337 | E15: 1.1286438
A16: Sun Pharma | B16: 3.2751776 | C16: 3.3456176 | D16: 0.10864506 | E16: 1.0215072
A17: Torrent | B17: 2.9109611 | C17: 3.3485254 | D17: 0.098457465 | E17: 1.1503161
A18: Grand Total | B18: 18.650082 | C18: 19.882429 | D18: 0.65739005 | E18: 6.3414265
